{
  "date": "2025-12-12",
  "events": [
    {
      "title": "1. FC Union Berlin vs RB Leipzig",
      "time": "20:30",
      "iso_time": "",
      "sport": "Fußball",
      "sport_slug": "fussball",
      "sender": "Sportschau Live",
      "sender_slug": "sportschau-live",
      "link": "https://www.sportschau.de/live-und-ergebnisse/fussball/deutschland-bundesliga/ma11200919/1-fc-union-berlin_rb-leipzig/info",
      "slug": "1-fc-union-berlin-vs-rb-leipzig",
      "subtitle": "",
      "related_events": []
    },
    {
      "title": "SpVgg Greuther Fürth vs Hertha BSC",
      "time": "18:30",
      "iso_time": "",
      "sport": "Fußball",
      "sport_slug": "fussball",
      "sender": "Sportschau Live",
      "sender_slug": "sportschau-live",
      "link": "https://www.sportschau.de/live-und-ergebnisse/fussball/deutschland-2-bundesliga/ma11201321/spvgg-greuther-fuerth_hertha-bsc/info",
      "slug": "spvgg-greuther-furth-vs-hertha-bsc",
      "subtitle": "",
      "related_events": [
        {
          "title": "Dynamo Dresden vs Eintracht Braunschweig",
          "time": "18:30",
          "sender": "Sportschau Live",
          "slug": "dynamo-dresden-vs-eintracht-braunschweig"
        },
        {
          "title": "Werder Bremen vs Bayer Leverkusen",
          "time": "18:30",
          "sender": "Sportschau Live",
          "slug": "werder-bremen-vs-bayer-leverkusen"
        }
      ]
    },
    {
      "title": "Dynamo Dresden vs Eintracht Braunschweig",
      "time": "18:30",
      "iso_time": "",
      "sport": "Fußball",
      "sport_slug": "fussball",
      "sender": "Sportschau Live",
      "sender_slug": "sportschau-live",
      "link": "https://www.sportschau.de/live-und-ergebnisse/fussball/deutschland-2-bundesliga/ma11201357/dynamo-dresden_eintracht-braunschweig/info",
      "slug": "dynamo-dresden-vs-eintracht-braunschweig",
      "subtitle": "",
      "related_events": [
        {
          "title": "SpVgg Greuther Fürth vs Hertha BSC",
          "time": "18:30",
          "sender": "Sportschau Live",
          "slug": "spvgg-greuther-furth-vs-hertha-bsc"
        },
        {
          "title": "Werder Bremen vs Bayer Leverkusen",
          "time": "18:30",
          "sender": "Sportschau Live",
          "slug": "werder-bremen-vs-bayer-leverkusen"
        }
      ]
    },
    {
      "title": "Werder Bremen vs Bayer Leverkusen",
      "time": "18:30",
      "iso_time": "",
      "sport": "Fußball",
      "sport_slug": "fussball",
      "sender": "Sportschau Live",
      "sender_slug": "sportschau-live",
      "link": "https://www.sportschau.de/live-und-ergebnisse/fussball/deutschland-bundesliga-frauen/ma11376623/werder-bremen_bayer-leverkusen/info",
      "slug": "werder-bremen-vs-bayer-leverkusen",
      "subtitle": "",
      "related_events": [
        {
          "title": "SpVgg Greuther Fürth vs Hertha BSC",
          "time": "18:30",
          "sender": "Sportschau Live",
          "slug": "spvgg-greuther-furth-vs-hertha-bsc"
        },
        {
          "title": "Dynamo Dresden vs Eintracht Braunschweig",
          "time": "18:30",
          "sender": "Sportschau Live",
          "slug": "dynamo-dresden-vs-eintracht-braunschweig"
        }
      ]
    },
    {
      "title": "SSV Ulm 1846 vs VfL Osnabrück",
      "time": "19:00",
      "iso_time": "",
      "sport": "Fußball",
      "sport_slug": "fussball",
      "sender": "Sportschau Live",
      "sender_slug": "sportschau-live",
      "link": "https://www.sportschau.de/live-und-ergebnisse/fussball/deutschland-3-liga/ma11237987/ssv-ulm-1846_vfl-osnabrueck/info",
      "slug": "ssv-ulm-1846-vs-vfl-osnabruck",
      "subtitle": "",
      "related_events": []
    },
    {
      "title": " vs ",
      "time": "14:15",
      "iso_time": "",
      "sport": "Biathlon",
      "sport_slug": "biathlon",
      "sender": "Sportschau Live",
      "sender_slug": "sportschau-live",
      "link": "https://www.sportschau.de/live-und-ergebnisse/biathlon/co732/hochfilzen/ma11436917/ergebnisse",
      "slug": "vs",
      "subtitle": "",
      "related_events": [
        {
          "title": "Hochfilzen | 7,5km Sprint",
          "time": "14:15",
          "sender": "Eurosport",
          "slug": "hochfilzen-75km-sprint"
        }
      ]
    },
    {
      "title": " vs ",
      "time": "11:25",
      "iso_time": "",
      "sport": "Biathlon",
      "sport_slug": "biathlon",
      "sender": "Sportschau Live",
      "sender_slug": "sportschau-live",
      "link": "https://www.sportschau.de/live-und-ergebnisse/biathlon/co721/hochfilzen/ma11436908/ergebnisse",
      "slug": "vs",
      "subtitle": "",
      "related_events": []
    },
    {
      "title": " vs ",
      "time": "15:35",
      "iso_time": "",
      "sport": "Skispringen",
      "sport_slug": "skispringen",
      "sender": "Sportschau Live",
      "sender_slug": "sportschau-live",
      "link": "https://www.sportschau.de/live-und-ergebnisse/skispringen/co5480/klingenthal/ma11582900/ergebnisse",
      "slug": "vs",
      "subtitle": "",
      "related_events": [
        {
          "title": "Klingenthal | Einzelspringen",
          "time": "15:35",
          "sender": "Eurosport",
          "slug": "klingenthal-einzelspringen"
        }
      ]
    },
    {
      "title": " vs ",
      "time": "10:15",
      "iso_time": "",
      "sport": "Ski Alpin",
      "sport_slug": "ski-alpin",
      "sender": "Sportschau Live",
      "sender_slug": "sportschau-live",
      "link": "https://www.sportschau.de/live-und-ergebnisse/ski-alpin/co815/st-moritz/ma11587265/ergebnisse",
      "slug": "vs",
      "subtitle": "",
      "related_events": []
    },
    {
      "title": "Frankreich vs Deutschland",
      "time": "17:45",
      "iso_time": "",
      "sport": "Handball",
      "sport_slug": "handball",
      "sender": "Sportschau Live",
      "sender_slug": "sportschau-live",
      "link": "https://www.sportschau.de/live-und-ergebnisse/handball/ihf-wm-frauen/ma11101874/frankreich_deutschland/info",
      "slug": "frankreich-vs-deutschland",
      "subtitle": "",
      "related_events": []
    },
    {
      "title": "Niederlande vs Norwegen",
      "time": "20:45",
      "iso_time": "",
      "sport": "Handball",
      "sport_slug": "handball",
      "sender": "Sportschau Live",
      "sender_slug": "sportschau-live",
      "link": "https://www.sportschau.de/live-und-ergebnisse/handball/ihf-wm-frauen/ma11101877/niederlande_norwegen/info",
      "slug": "niederlande-vs-norwegen",
      "subtitle": "",
      "related_events": []
    },
    {
      "title": " vs ",
      "time": "17:00",
      "iso_time": "",
      "sport": "Ski Langlauf",
      "sport_slug": "ski-langlauf",
      "sender": "Sportschau Live",
      "sender_slug": "sportschau-live",
      "link": "https://www.sportschau.de/live-und-ergebnisse/langlauf/co14852/davos/ma11587556/ergebnisse",
      "slug": "vs",
      "subtitle": "",
      "related_events": []
    },
    {
      "title": " vs ",
      "time": "17:00",
      "iso_time": "",
      "sport": "Ski Langlauf",
      "sport_slug": "ski-langlauf",
      "sender": "Sportschau Live",
      "sender_slug": "sportschau-live",
      "link": "https://www.sportschau.de/live-und-ergebnisse/langlauf/co14849/davos/ma11587553/ergebnisse",
      "slug": "vs",
      "subtitle": "",
      "related_events": []
    },
    {
      "title": " vs ",
      "time": "23:10",
      "iso_time": "",
      "sport": "Rodeln",
      "sport_slug": "rodeln",
      "sender": "Sportschau Live",
      "sender_slug": "sportschau-live",
      "link": "https://www.sportschau.de/live-und-ergebnisse/rodeln/co3613/park-city/ma11593835/ergebnisse",
      "slug": "vs",
      "subtitle": "",
      "related_events": []
    },
    {
      "title": "Paris Saint-Germain vs Montpellier HSC",
      "time": "21:00",
      "iso_time": "",
      "sport": "Fußball",
      "sport_slug": "fussball",
      "sender": "Sportschau Live",
      "sender_slug": "sportschau-live",
      "link": "https://www.sportschau.de/live-und-ergebnisse/fussball/frankreich-frauen-division-1/ma11397101/paris-saint-germain_montpellier-hsc/info",
      "slug": "paris-saint-germain-vs-montpellier-hsc",
      "subtitle": "",
      "related_events": [
        {
          "title": "Real Sociedad San Sebastian vs Girona FC",
          "time": "21:00",
          "sender": "Sportschau Live",
          "slug": "real-sociedad-san-sebastian-vs-girona-fc"
        }
      ]
    },
    {
      "title": "NINERS Chemnitz vs Fitness First Würzburg Baskets",
      "time": "20:00",
      "iso_time": "",
      "sport": "Basketball",
      "sport_slug": "basketball",
      "sender": "Sportschau Live",
      "sender_slug": "sportschau-live",
      "link": "https://www.sportschau.de/live-und-ergebnisse/basketball/deutschland-bbl/ma11487497/niners-chemnitz_fitness-first-wuerzburg-baskets/info",
      "slug": "niners-chemnitz-vs-fitness-first-wurzburg-baskets",
      "subtitle": "",
      "related_events": []
    },
    {
      "title": "Dubai Basketball vs FC Bayern München",
      "time": "17:00",
      "iso_time": "",
      "sport": "Basketball",
      "sport_slug": "basketball",
      "sender": "Sportschau Live",
      "sender_slug": "sportschau-live",
      "link": "https://www.sportschau.de/live-und-ergebnisse/basketball/euroleague-basketball/ma11493101/dubai-basketball_fc-bayern-muenchen/info",
      "slug": "dubai-basketball-vs-fc-bayern-munchen",
      "subtitle": "",
      "related_events": []
    },
    {
      "title": "AS Monaco vs Fenerbahçe",
      "time": "19:30",
      "iso_time": "",
      "sport": "Basketball",
      "sport_slug": "basketball",
      "sender": "Sportschau Live",
      "sender_slug": "sportschau-live",
      "link": "https://www.sportschau.de/live-und-ergebnisse/basketball/euroleague-basketball/ma11493104/as-monaco_fenerbahce/info",
      "slug": "as-monaco-vs-fenerbahce",
      "subtitle": "",
      "related_events": []
    },
    {
      "title": "FC Barcelona vs Olympiakos Piraeus",
      "time": "20:30",
      "iso_time": "",
      "sport": "Basketball",
      "sport_slug": "basketball",
      "sender": "Sportschau Live",
      "sender_slug": "sportschau-live",
      "link": "https://www.sportschau.de/live-und-ergebnisse/basketball/euroleague-basketball/ma11493107/fc-barcelona_olympiakos-piraeus/info",
      "slug": "fc-barcelona-vs-olympiakos-piraeus",
      "subtitle": "",
      "related_events": [
        {
          "title": "KK Partizan vs KK Crvena Zvezda",
          "time": "20:30",
          "sender": "Sportschau Live",
          "slug": "kk-partizan-vs-kk-crvena-zvezda"
        },
        {
          "title": "Virtus Bologna vs Hapoel Tel Aviv",
          "time": "20:30",
          "sender": "Sportschau Live",
          "slug": "virtus-bologna-vs-hapoel-tel-aviv"
        }
      ]
    },
    {
      "title": "KK Partizan vs KK Crvena Zvezda",
      "time": "20:30",
      "iso_time": "",
      "sport": "Basketball",
      "sport_slug": "basketball",
      "sender": "Sportschau Live",
      "sender_slug": "sportschau-live",
      "link": "https://www.sportschau.de/live-und-ergebnisse/basketball/euroleague-basketball/ma11493110/kk-partizan_kk-crvena-zvezda/info",
      "slug": "kk-partizan-vs-kk-crvena-zvezda",
      "subtitle": "",
      "related_events": [
        {
          "title": "FC Barcelona vs Olympiakos Piraeus",
          "time": "20:30",
          "sender": "Sportschau Live",
          "slug": "fc-barcelona-vs-olympiakos-piraeus"
        },
        {
          "title": "Virtus Bologna vs Hapoel Tel Aviv",
          "time": "20:30",
          "sender": "Sportschau Live",
          "slug": "virtus-bologna-vs-hapoel-tel-aviv"
        }
      ]
    },
    {
      "title": "Virtus Bologna vs Hapoel Tel Aviv",
      "time": "20:30",
      "iso_time": "",
      "sport": "Basketball",
      "sport_slug": "basketball",
      "sender": "Sportschau Live",
      "sender_slug": "sportschau-live",
      "link": "https://www.sportschau.de/live-und-ergebnisse/basketball/euroleague-basketball/ma11493113/virtus-bologna_hapoel-tel-aviv/info",
      "slug": "virtus-bologna-vs-hapoel-tel-aviv",
      "subtitle": "",
      "related_events": [
        {
          "title": "FC Barcelona vs Olympiakos Piraeus",
          "time": "20:30",
          "sender": "Sportschau Live",
          "slug": "fc-barcelona-vs-olympiakos-piraeus"
        },
        {
          "title": "KK Partizan vs KK Crvena Zvezda",
          "time": "20:30",
          "sender": "Sportschau Live",
          "slug": "kk-partizan-vs-kk-crvena-zvezda"
        }
      ]
    },
    {
      "title": "Straubing Tigers vs Eisbären Berlin",
      "time": "19:30",
      "iso_time": "",
      "sport": "Eishockey",
      "sport_slug": "eishockey",
      "sender": "Sportschau Live",
      "sender_slug": "sportschau-live",
      "link": "https://www.sportschau.de/live-und-ergebnisse/eishockey/deutschland-del/ma11212088/straubing-tigers_eisbaeren-berlin/info",
      "slug": "straubing-tigers-vs-eisbaren-berlin",
      "subtitle": "",
      "related_events": [
        {
          "title": "Schwenninger Wild Wings vs Adler Mannheim",
          "time": "19:30",
          "sender": "Sportschau Live",
          "slug": "schwenninger-wild-wings-vs-adler-mannheim"
        },
        {
          "title": "Grizzlys Wolfsburg vs Fischtown Pinguins",
          "time": "19:30",
          "sender": "Sportschau Live",
          "slug": "grizzlys-wolfsburg-vs-fischtown-pinguins"
        },
        {
          "title": "Iserlohn Roosters vs Dresdner Eislöwen",
          "time": "19:30",
          "sender": "Sportschau Live",
          "slug": "iserlohn-roosters-vs-dresdner-eislowen"
        }
      ]
    },
    {
      "title": "Schwenninger Wild Wings vs Adler Mannheim",
      "time": "19:30",
      "iso_time": "",
      "sport": "Eishockey",
      "sport_slug": "eishockey",
      "sender": "Sportschau Live",
      "sender_slug": "sportschau-live",
      "link": "https://www.sportschau.de/live-und-ergebnisse/eishockey/deutschland-del/ma11212094/schwenninger-wild-wings_adler-mannheim/info",
      "slug": "schwenninger-wild-wings-vs-adler-mannheim",
      "subtitle": "",
      "related_events": [
        {
          "title": "Straubing Tigers vs Eisbären Berlin",
          "time": "19:30",
          "sender": "Sportschau Live",
          "slug": "straubing-tigers-vs-eisbaren-berlin"
        },
        {
          "title": "Grizzlys Wolfsburg vs Fischtown Pinguins",
          "time": "19:30",
          "sender": "Sportschau Live",
          "slug": "grizzlys-wolfsburg-vs-fischtown-pinguins"
        },
        {
          "title": "Iserlohn Roosters vs Dresdner Eislöwen",
          "time": "19:30",
          "sender": "Sportschau Live",
          "slug": "iserlohn-roosters-vs-dresdner-eislowen"
        }
      ]
    },
    {
      "title": "Grizzlys Wolfsburg vs Fischtown Pinguins",
      "time": "19:30",
      "iso_time": "",
      "sport": "Eishockey",
      "sport_slug": "eishockey",
      "sender": "Sportschau Live",
      "sender_slug": "sportschau-live",
      "link": "https://www.sportschau.de/live-und-ergebnisse/eishockey/deutschland-del/ma11212100/grizzlys-wolfsburg_fischtown-pinguins/info",
      "slug": "grizzlys-wolfsburg-vs-fischtown-pinguins",
      "subtitle": "",
      "related_events": [
        {
          "title": "Straubing Tigers vs Eisbären Berlin",
          "time": "19:30",
          "sender": "Sportschau Live",
          "slug": "straubing-tigers-vs-eisbaren-berlin"
        },
        {
          "title": "Schwenninger Wild Wings vs Adler Mannheim",
          "time": "19:30",
          "sender": "Sportschau Live",
          "slug": "schwenninger-wild-wings-vs-adler-mannheim"
        },
        {
          "title": "Iserlohn Roosters vs Dresdner Eislöwen",
          "time": "19:30",
          "sender": "Sportschau Live",
          "slug": "iserlohn-roosters-vs-dresdner-eislowen"
        }
      ]
    },
    {
      "title": "Iserlohn Roosters vs Dresdner Eislöwen",
      "time": "19:30",
      "iso_time": "",
      "sport": "Eishockey",
      "sport_slug": "eishockey",
      "sender": "Sportschau Live",
      "sender_slug": "sportschau-live",
      "link": "https://www.sportschau.de/live-und-ergebnisse/eishockey/deutschland-del/ma11212106/iserlohn-roosters_dresdner-eisloewen/info",
      "slug": "iserlohn-roosters-vs-dresdner-eislowen",
      "subtitle": "",
      "related_events": [
        {
          "title": "Straubing Tigers vs Eisbären Berlin",
          "time": "19:30",
          "sender": "Sportschau Live",
          "slug": "straubing-tigers-vs-eisbaren-berlin"
        },
        {
          "title": "Schwenninger Wild Wings vs Adler Mannheim",
          "time": "19:30",
          "sender": "Sportschau Live",
          "slug": "schwenninger-wild-wings-vs-adler-mannheim"
        },
        {
          "title": "Grizzlys Wolfsburg vs Fischtown Pinguins",
          "time": "19:30",
          "sender": "Sportschau Live",
          "slug": "grizzlys-wolfsburg-vs-fischtown-pinguins"
        }
      ]
    },
    {
      "title": "Augsburger Panther vs ERC Ingolstadt",
      "time": "19:30",
      "iso_time": "",
      "sport": "Eishockey",
      "sport_slug": "eishockey",
      "sender": "Sportschau Live",
      "sender_slug": "sportschau-live",
      "link": "https://www.sportschau.de/live-und-ergebnisse/eishockey/deutschland-del/ma11212109/augsburger-panther_erc-ingolstadt/info",
      "slug": "augsburger-panther-vs-erc-ingolstadt",
      "subtitle": "",
      "related_events": [
        {
          "title": "Straubing Tigers vs Eisbären Berlin",
          "time": "19:30",
          "sender": "Sportschau Live",
          "slug": "straubing-tigers-vs-eisbaren-berlin"
        },
        {
          "title": "Schwenninger Wild Wings vs Adler Mannheim",
          "time": "19:30",
          "sender": "Sportschau Live",
          "slug": "schwenninger-wild-wings-vs-adler-mannheim"
        },
        {
          "title": "Grizzlys Wolfsburg vs Fischtown Pinguins",
          "time": "19:30",
          "sender": "Sportschau Live",
          "slug": "grizzlys-wolfsburg-vs-fischtown-pinguins"
        }
      ]
    },
    {
      "title": "Nürnberg Ice Tigers vs Löwen Frankfurt",
      "time": "19:30",
      "iso_time": "",
      "sport": "Eishockey",
      "sport_slug": "eishockey",
      "sender": "Sportschau Live",
      "sender_slug": "sportschau-live",
      "link": "https://www.sportschau.de/live-und-ergebnisse/eishockey/deutschland-del/ma11212115/nuernberg-ice-tigers_loewen-frankfurt/info",
      "slug": "nurnberg-ice-tigers-vs-lowen-frankfurt",
      "subtitle": "",
      "related_events": [
        {
          "title": "Straubing Tigers vs Eisbären Berlin",
          "time": "19:30",
          "sender": "Sportschau Live",
          "slug": "straubing-tigers-vs-eisbaren-berlin"
        },
        {
          "title": "Schwenninger Wild Wings vs Adler Mannheim",
          "time": "19:30",
          "sender": "Sportschau Live",
          "slug": "schwenninger-wild-wings-vs-adler-mannheim"
        },
        {
          "title": "Grizzlys Wolfsburg vs Fischtown Pinguins",
          "time": "19:30",
          "sender": "Sportschau Live",
          "slug": "grizzlys-wolfsburg-vs-fischtown-pinguins"
        }
      ]
    },
    {
      "title": "Eispiraten Crimmitschau vs Blue Devils Weiden",
      "time": "19:30",
      "iso_time": "",
      "sport": "Eishockey",
      "sport_slug": "eishockey",
      "sender": "Sportschau Live",
      "sender_slug": "sportschau-live",
      "link": "https://www.sportschau.de/live-und-ergebnisse/eishockey/deutschland-del-2/ma11210687/eispiraten-crimmitschau_blue-devils-weiden/info",
      "slug": "eispiraten-crimmitschau-vs-blue-devils-weiden",
      "subtitle": "",
      "related_events": [
        {
          "title": "Straubing Tigers vs Eisbären Berlin",
          "time": "19:30",
          "sender": "Sportschau Live",
          "slug": "straubing-tigers-vs-eisbaren-berlin"
        },
        {
          "title": "Schwenninger Wild Wings vs Adler Mannheim",
          "time": "19:30",
          "sender": "Sportschau Live",
          "slug": "schwenninger-wild-wings-vs-adler-mannheim"
        },
        {
          "title": "Grizzlys Wolfsburg vs Fischtown Pinguins",
          "time": "19:30",
          "sender": "Sportschau Live",
          "slug": "grizzlys-wolfsburg-vs-fischtown-pinguins"
        }
      ]
    },
    {
      "title": "Düsseldorfer EG vs Bietigheim Steelers",
      "time": "19:30",
      "iso_time": "",
      "sport": "Eishockey",
      "sport_slug": "eishockey",
      "sender": "Sportschau Live",
      "sender_slug": "sportschau-live",
      "link": "https://www.sportschau.de/live-und-ergebnisse/eishockey/deutschland-del-2/ma11210690/duesseldorfer-eg_bietigheim-steelers/info",
      "slug": "dusseldorfer-eg-vs-bietigheim-steelers",
      "subtitle": "",
      "related_events": [
        {
          "title": "Straubing Tigers vs Eisbären Berlin",
          "time": "19:30",
          "sender": "Sportschau Live",
          "slug": "straubing-tigers-vs-eisbaren-berlin"
        },
        {
          "title": "Schwenninger Wild Wings vs Adler Mannheim",
          "time": "19:30",
          "sender": "Sportschau Live",
          "slug": "schwenninger-wild-wings-vs-adler-mannheim"
        },
        {
          "title": "Grizzlys Wolfsburg vs Fischtown Pinguins",
          "time": "19:30",
          "sender": "Sportschau Live",
          "slug": "grizzlys-wolfsburg-vs-fischtown-pinguins"
        }
      ]
    },
    {
      "title": "EV Landshut vs ESV Kaufbeuren",
      "time": "19:30",
      "iso_time": "",
      "sport": "Eishockey",
      "sport_slug": "eishockey",
      "sender": "Sportschau Live",
      "sender_slug": "sportschau-live",
      "link": "https://www.sportschau.de/live-und-ergebnisse/eishockey/deutschland-del-2/ma11210693/ev-landshut_esv-kaufbeuren/info",
      "slug": "ev-landshut-vs-esv-kaufbeuren",
      "subtitle": "",
      "related_events": [
        {
          "title": "Straubing Tigers vs Eisbären Berlin",
          "time": "19:30",
          "sender": "Sportschau Live",
          "slug": "straubing-tigers-vs-eisbaren-berlin"
        },
        {
          "title": "Schwenninger Wild Wings vs Adler Mannheim",
          "time": "19:30",
          "sender": "Sportschau Live",
          "slug": "schwenninger-wild-wings-vs-adler-mannheim"
        },
        {
          "title": "Grizzlys Wolfsburg vs Fischtown Pinguins",
          "time": "19:30",
          "sender": "Sportschau Live",
          "slug": "grizzlys-wolfsburg-vs-fischtown-pinguins"
        }
      ]
    },
    {
      "title": "EC Kassel Huskies vs Starbulls Rosenheim",
      "time": "19:30",
      "iso_time": "",
      "sport": "Eishockey",
      "sport_slug": "eishockey",
      "sender": "Sportschau Live",
      "sender_slug": "sportschau-live",
      "link": "https://www.sportschau.de/live-und-ergebnisse/eishockey/deutschland-del-2/ma11210696/ec-kassel-huskies_starbulls-rosenheim/info",
      "slug": "ec-kassel-huskies-vs-starbulls-rosenheim",
      "subtitle": "",
      "related_events": [
        {
          "title": "Straubing Tigers vs Eisbären Berlin",
          "time": "19:30",
          "sender": "Sportschau Live",
          "slug": "straubing-tigers-vs-eisbaren-berlin"
        },
        {
          "title": "Schwenninger Wild Wings vs Adler Mannheim",
          "time": "19:30",
          "sender": "Sportschau Live",
          "slug": "schwenninger-wild-wings-vs-adler-mannheim"
        },
        {
          "title": "Grizzlys Wolfsburg vs Fischtown Pinguins",
          "time": "19:30",
          "sender": "Sportschau Live",
          "slug": "grizzlys-wolfsburg-vs-fischtown-pinguins"
        }
      ]
    },
    {
      "title": "EC Bad Nauheim vs Eisbären Regensburg",
      "time": "19:30",
      "iso_time": "",
      "sport": "Eishockey",
      "sport_slug": "eishockey",
      "sender": "Sportschau Live",
      "sender_slug": "sportschau-live",
      "link": "https://www.sportschau.de/live-und-ergebnisse/eishockey/deutschland-del-2/ma11210699/ec-bad-nauheim_eisbaeren-regensburg/info",
      "slug": "ec-bad-nauheim-vs-eisbaren-regensburg",
      "subtitle": "",
      "related_events": [
        {
          "title": "Straubing Tigers vs Eisbären Berlin",
          "time": "19:30",
          "sender": "Sportschau Live",
          "slug": "straubing-tigers-vs-eisbaren-berlin"
        },
        {
          "title": "Schwenninger Wild Wings vs Adler Mannheim",
          "time": "19:30",
          "sender": "Sportschau Live",
          "slug": "schwenninger-wild-wings-vs-adler-mannheim"
        },
        {
          "title": "Grizzlys Wolfsburg vs Fischtown Pinguins",
          "time": "19:30",
          "sender": "Sportschau Live",
          "slug": "grizzlys-wolfsburg-vs-fischtown-pinguins"
        }
      ]
    },
    {
      "title": "EHC Freiburg vs Ravensburg Towerstars",
      "time": "19:30",
      "iso_time": "",
      "sport": "Eishockey",
      "sport_slug": "eishockey",
      "sender": "Sportschau Live",
      "sender_slug": "sportschau-live",
      "link": "https://www.sportschau.de/live-und-ergebnisse/eishockey/deutschland-del-2/ma11210702/ehc-freiburg_ravensburg-towerstars/info",
      "slug": "ehc-freiburg-vs-ravensburg-towerstars",
      "subtitle": "",
      "related_events": [
        {
          "title": "Straubing Tigers vs Eisbären Berlin",
          "time": "19:30",
          "sender": "Sportschau Live",
          "slug": "straubing-tigers-vs-eisbaren-berlin"
        },
        {
          "title": "Schwenninger Wild Wings vs Adler Mannheim",
          "time": "19:30",
          "sender": "Sportschau Live",
          "slug": "schwenninger-wild-wings-vs-adler-mannheim"
        },
        {
          "title": "Grizzlys Wolfsburg vs Fischtown Pinguins",
          "time": "19:30",
          "sender": "Sportschau Live",
          "slug": "grizzlys-wolfsburg-vs-fischtown-pinguins"
        }
      ]
    },
    {
      "title": "Lausitzer Füchse vs Krefeld Pinguine",
      "time": "19:30",
      "iso_time": "",
      "sport": "Eishockey",
      "sport_slug": "eishockey",
      "sender": "Sportschau Live",
      "sender_slug": "sportschau-live",
      "link": "https://www.sportschau.de/live-und-ergebnisse/eishockey/deutschland-del-2/ma11210705/lausitzer-fuechse_krefeld-pinguine/info",
      "slug": "lausitzer-fuchse-vs-krefeld-pinguine",
      "subtitle": "",
      "related_events": [
        {
          "title": "Straubing Tigers vs Eisbären Berlin",
          "time": "19:30",
          "sender": "Sportschau Live",
          "slug": "straubing-tigers-vs-eisbaren-berlin"
        },
        {
          "title": "Schwenninger Wild Wings vs Adler Mannheim",
          "time": "19:30",
          "sender": "Sportschau Live",
          "slug": "schwenninger-wild-wings-vs-adler-mannheim"
        },
        {
          "title": "Grizzlys Wolfsburg vs Fischtown Pinguins",
          "time": "19:30",
          "sender": "Sportschau Live",
          "slug": "grizzlys-wolfsburg-vs-fischtown-pinguins"
        }
      ]
    },
    {
      "title": " vs ",
      "time": "13:00",
      "iso_time": "",
      "sport": "Skeleton",
      "sport_slug": "skeleton",
      "sender": "Sportschau Live",
      "sender_slug": "sportschau-live",
      "link": "https://www.sportschau.de/live-und-ergebnisse/skeleton/co11114/lillehammer/ma11473496/ergebnisse",
      "slug": "vs",
      "subtitle": "",
      "related_events": []
    },
    {
      "title": " vs ",
      "time": "09:00",
      "iso_time": "",
      "sport": "Skeleton",
      "sport_slug": "skeleton",
      "sender": "Sportschau Live",
      "sender_slug": "sportschau-live",
      "link": "https://www.sportschau.de/live-und-ergebnisse/skeleton/co11111/lillehammer/ma11473493/ergebnisse",
      "slug": "vs",
      "subtitle": "",
      "related_events": []
    },
    {
      "title": " vs ",
      "time": "17:00",
      "iso_time": "",
      "sport": "Skeleton",
      "sport_slug": "skeleton",
      "sender": "Sportschau Live",
      "sender_slug": "sportschau-live",
      "link": "https://www.sportschau.de/live-und-ergebnisse/skeleton/co14660/lillehammer/ma11473499/ergebnisse",
      "slug": "vs",
      "subtitle": "",
      "related_events": []
    },
    {
      "title": "Real Sociedad San Sebastian vs Girona FC",
      "time": "21:00",
      "iso_time": "",
      "sport": "Fußball",
      "sport_slug": "fussball",
      "sender": "Sportschau Live",
      "sender_slug": "sportschau-live",
      "link": "https://www.sportschau.de/live-und-ergebnisse/fussball/spanien-primera-division/ma11223341/real-sociedad-san-sebastian_girona-fc/info",
      "slug": "real-sociedad-san-sebastian-vs-girona-fc",
      "subtitle": "",
      "related_events": [
        {
          "title": "Paris Saint-Germain vs Montpellier HSC",
          "time": "21:00",
          "sender": "Sportschau Live",
          "slug": "paris-saint-germain-vs-montpellier-hsc"
        }
      ]
    },
    {
      "title": "Angers SCO vs FC Nantes",
      "time": "20:45",
      "iso_time": "",
      "sport": "Fußball",
      "sport_slug": "fussball",
      "sender": "Sportschau Live",
      "sender_slug": "sportschau-live",
      "link": "https://www.sportschau.de/live-und-ergebnisse/fussball/frankreich-ligue-1/ma11204348/angers-sco_fc-nantes/info",
      "slug": "angers-sco-vs-fc-nantes",
      "subtitle": "",
      "related_events": [
        {
          "title": "US Lecce vs Pisa SC",
          "time": "20:45",
          "sender": "Sportschau Live",
          "slug": "us-lecce-vs-pisa-sc"
        },
        {
          "title": "Standard Lüttich vs Oud-Heverlee Leuven",
          "time": "20:45",
          "sender": "Sportschau Live",
          "slug": "standard-luttich-vs-oud-heverlee-leuven"
        }
      ]
    },
    {
      "title": "US Lecce vs Pisa SC",
      "time": "20:45",
      "iso_time": "",
      "sport": "Fußball",
      "sport_slug": "fussball",
      "sender": "Sportschau Live",
      "sender_slug": "sportschau-live",
      "link": "https://www.sportschau.de/live-und-ergebnisse/fussball/italien-serie-a/ma11129037/us-lecce_pisa-sc/info",
      "slug": "us-lecce-vs-pisa-sc",
      "subtitle": "",
      "related_events": [
        {
          "title": "Angers SCO vs FC Nantes",
          "time": "20:45",
          "sender": "Sportschau Live",
          "slug": "angers-sco-vs-fc-nantes"
        },
        {
          "title": "Standard Lüttich vs Oud-Heverlee Leuven",
          "time": "20:45",
          "sender": "Sportschau Live",
          "slug": "standard-luttich-vs-oud-heverlee-leuven"
        }
      ]
    },
    {
      "title": "Kasımpaşa SK vs Gençlerbirliği",
      "time": "18:00",
      "iso_time": "",
      "sport": "Fußball",
      "sport_slug": "fussball",
      "sender": "Sportschau Live",
      "sender_slug": "sportschau-live",
      "link": "https://www.sportschau.de/live-und-ergebnisse/fussball/tuerkei-sueper-lig/ma11303168/kasimpasa-sk_genclerbirligi/info",
      "slug": "kasimpasa-sk-vs-genclerbirligi",
      "subtitle": "",
      "related_events": []
    },
    {
      "title": "Standard Lüttich vs Oud-Heverlee Leuven",
      "time": "20:45",
      "iso_time": "",
      "sport": "Fußball",
      "sport_slug": "fussball",
      "sender": "Sportschau Live",
      "sender_slug": "sportschau-live",
      "link": "https://www.sportschau.de/live-und-ergebnisse/fussball/belgien-eerste-klasse/ma11166345/standard-luettich_oud-heverlee-leuven/info",
      "slug": "standard-luttich-vs-oud-heverlee-leuven",
      "subtitle": "",
      "related_events": [
        {
          "title": "Angers SCO vs FC Nantes",
          "time": "20:45",
          "sender": "Sportschau Live",
          "slug": "angers-sco-vs-fc-nantes"
        },
        {
          "title": "US Lecce vs Pisa SC",
          "time": "20:45",
          "sender": "Sportschau Live",
          "slug": "us-lecce-vs-pisa-sc"
        }
      ]
    },
    {
      "title": "Houston Rockets vs Los Angeles Clippers",
      "time": "02:00",
      "iso_time": "",
      "sport": "Basketball",
      "sport_slug": "basketball",
      "sender": "Sportschau Live",
      "sender_slug": "sportschau-live",
      "link": "https://www.sportschau.de/live-und-ergebnisse/basketball/usa-nba/ma11744980/houston-rockets_los-angeles-clippers/info",
      "slug": "houston-rockets-vs-los-angeles-clippers",
      "subtitle": "",
      "related_events": [
        {
          "title": "Milwaukee Bucks vs Boston Celtics",
          "time": "02:00",
          "sender": "Sportschau Live",
          "slug": "milwaukee-bucks-vs-boston-celtics"
        },
        {
          "title": "New Orleans Pelicans vs Portland Trail Blazers",
          "time": "02:00",
          "sender": "Sportschau Live",
          "slug": "new-orleans-pelicans-vs-portland-trail-blazers"
        }
      ]
    },
    {
      "title": "Milwaukee Bucks vs Boston Celtics",
      "time": "02:00",
      "iso_time": "",
      "sport": "Basketball",
      "sport_slug": "basketball",
      "sender": "Sportschau Live",
      "sender_slug": "sportschau-live",
      "link": "https://www.sportschau.de/live-und-ergebnisse/basketball/usa-nba/ma11744983/milwaukee-bucks_boston-celtics/info",
      "slug": "milwaukee-bucks-vs-boston-celtics",
      "subtitle": "",
      "related_events": [
        {
          "title": "Houston Rockets vs Los Angeles Clippers",
          "time": "02:00",
          "sender": "Sportschau Live",
          "slug": "houston-rockets-vs-los-angeles-clippers"
        },
        {
          "title": "New Orleans Pelicans vs Portland Trail Blazers",
          "time": "02:00",
          "sender": "Sportschau Live",
          "slug": "new-orleans-pelicans-vs-portland-trail-blazers"
        }
      ]
    },
    {
      "title": "New Orleans Pelicans vs Portland Trail Blazers",
      "time": "02:00",
      "iso_time": "",
      "sport": "Basketball",
      "sport_slug": "basketball",
      "sender": "Sportschau Live",
      "sender_slug": "sportschau-live",
      "link": "https://www.sportschau.de/live-und-ergebnisse/basketball/usa-nba/ma11744986/new-orleans-pelicans_portland-trail-blazers/info",
      "slug": "new-orleans-pelicans-vs-portland-trail-blazers",
      "subtitle": "",
      "related_events": [
        {
          "title": "Houston Rockets vs Los Angeles Clippers",
          "time": "02:00",
          "sender": "Sportschau Live",
          "slug": "houston-rockets-vs-los-angeles-clippers"
        },
        {
          "title": "Milwaukee Bucks vs Boston Celtics",
          "time": "02:00",
          "sender": "Sportschau Live",
          "slug": "milwaukee-bucks-vs-boston-celtics"
        }
      ]
    },
    {
      "title": "Sacramento Kings vs Denver Nuggets",
      "time": "04:00",
      "iso_time": "",
      "sport": "Basketball",
      "sport_slug": "basketball",
      "sender": "Sportschau Live",
      "sender_slug": "sportschau-live",
      "link": "https://www.sportschau.de/live-und-ergebnisse/basketball/usa-nba/ma11744989/sacramento-kings_denver-nuggets/info",
      "slug": "sacramento-kings-vs-denver-nuggets",
      "subtitle": "",
      "related_events": []
    },
    {
      "title": "Tampa Bay Buccaneers vs Atlanta Falcons",
      "time": "02:15",
      "iso_time": "",
      "sport": "American Football",
      "sport_slug": "american-football",
      "sender": "Sportschau Live",
      "sender_slug": "sportschau-live",
      "link": "https://www.sportschau.de/live-und-ergebnisse/football/usa-nfl/ma11091740/tampa-bay-buccaneers_atlanta-falcons/info",
      "slug": "tampa-bay-buccaneers-vs-atlanta-falcons",
      "subtitle": "",
      "related_events": []
    },
    {
      "title": "Columbus Blue Jackets vs Ottawa Senators",
      "time": "01:00",
      "iso_time": "",
      "sport": "Eishockey",
      "sport_slug": "eishockey",
      "sender": "Sportschau Live",
      "sender_slug": "sportschau-live",
      "link": "https://www.sportschau.de/live-und-ergebnisse/eishockey/nhl/ma11413727/columbus-blue-jackets_ottawa-senators/info",
      "slug": "columbus-blue-jackets-vs-ottawa-senators",
      "subtitle": "",
      "related_events": [
        {
          "title": "New Jersey Devils vs Tampa Bay Lightning",
          "time": "01:00",
          "sender": "Sportschau Live",
          "slug": "new-jersey-devils-vs-tampa-bay-lightning"
        },
        {
          "title": "New York Islanders vs Anaheim Ducks",
          "time": "01:00",
          "sender": "Sportschau Live",
          "slug": "new-york-islanders-vs-anaheim-ducks"
        },
        {
          "title": "Philadelphia Flyers vs Vegas Golden Knights",
          "time": "01:00",
          "sender": "Sportschau Live",
          "slug": "philadelphia-flyers-vs-vegas-golden-knights"
        }
      ]
    },
    {
      "title": "New Jersey Devils vs Tampa Bay Lightning",
      "time": "01:00",
      "iso_time": "",
      "sport": "Eishockey",
      "sport_slug": "eishockey",
      "sender": "Sportschau Live",
      "sender_slug": "sportschau-live",
      "link": "https://www.sportschau.de/live-und-ergebnisse/eishockey/nhl/ma11413730/new-jersey-devils_tampa-bay-lightning/info",
      "slug": "new-jersey-devils-vs-tampa-bay-lightning",
      "subtitle": "",
      "related_events": [
        {
          "title": "Columbus Blue Jackets vs Ottawa Senators",
          "time": "01:00",
          "sender": "Sportschau Live",
          "slug": "columbus-blue-jackets-vs-ottawa-senators"
        },
        {
          "title": "New York Islanders vs Anaheim Ducks",
          "time": "01:00",
          "sender": "Sportschau Live",
          "slug": "new-york-islanders-vs-anaheim-ducks"
        },
        {
          "title": "Philadelphia Flyers vs Vegas Golden Knights",
          "time": "01:00",
          "sender": "Sportschau Live",
          "slug": "philadelphia-flyers-vs-vegas-golden-knights"
        }
      ]
    },
    {
      "title": "New York Islanders vs Anaheim Ducks",
      "time": "01:00",
      "iso_time": "",
      "sport": "Eishockey",
      "sport_slug": "eishockey",
      "sender": "Sportschau Live",
      "sender_slug": "sportschau-live",
      "link": "https://www.sportschau.de/live-und-ergebnisse/eishockey/nhl/ma11413733/new-york-islanders_anaheim-ducks/info",
      "slug": "new-york-islanders-vs-anaheim-ducks",
      "subtitle": "",
      "related_events": [
        {
          "title": "Columbus Blue Jackets vs Ottawa Senators",
          "time": "01:00",
          "sender": "Sportschau Live",
          "slug": "columbus-blue-jackets-vs-ottawa-senators"
        },
        {
          "title": "New Jersey Devils vs Tampa Bay Lightning",
          "time": "01:00",
          "sender": "Sportschau Live",
          "slug": "new-jersey-devils-vs-tampa-bay-lightning"
        },
        {
          "title": "Philadelphia Flyers vs Vegas Golden Knights",
          "time": "01:00",
          "sender": "Sportschau Live",
          "slug": "philadelphia-flyers-vs-vegas-golden-knights"
        }
      ]
    },
    {
      "title": "Philadelphia Flyers vs Vegas Golden Knights",
      "time": "01:00",
      "iso_time": "",
      "sport": "Eishockey",
      "sport_slug": "eishockey",
      "sender": "Sportschau Live",
      "sender_slug": "sportschau-live",
      "link": "https://www.sportschau.de/live-und-ergebnisse/eishockey/nhl/ma11413736/philadelphia-flyers_vegas-golden-knights/info",
      "slug": "philadelphia-flyers-vs-vegas-golden-knights",
      "subtitle": "",
      "related_events": [
        {
          "title": "Columbus Blue Jackets vs Ottawa Senators",
          "time": "01:00",
          "sender": "Sportschau Live",
          "slug": "columbus-blue-jackets-vs-ottawa-senators"
        },
        {
          "title": "New Jersey Devils vs Tampa Bay Lightning",
          "time": "01:00",
          "sender": "Sportschau Live",
          "slug": "new-jersey-devils-vs-tampa-bay-lightning"
        },
        {
          "title": "New York Islanders vs Anaheim Ducks",
          "time": "01:00",
          "sender": "Sportschau Live",
          "slug": "new-york-islanders-vs-anaheim-ducks"
        }
      ]
    },
    {
      "title": "Pittsburgh Penguins vs Montréal Canadiens",
      "time": "01:00",
      "iso_time": "",
      "sport": "Eishockey",
      "sport_slug": "eishockey",
      "sender": "Sportschau Live",
      "sender_slug": "sportschau-live",
      "link": "https://www.sportschau.de/live-und-ergebnisse/eishockey/nhl/ma11413739/pittsburgh-penguins_montreal-canadiens/info",
      "slug": "pittsburgh-penguins-vs-montreal-canadiens",
      "subtitle": "",
      "related_events": [
        {
          "title": "Columbus Blue Jackets vs Ottawa Senators",
          "time": "01:00",
          "sender": "Sportschau Live",
          "slug": "columbus-blue-jackets-vs-ottawa-senators"
        },
        {
          "title": "New Jersey Devils vs Tampa Bay Lightning",
          "time": "01:00",
          "sender": "Sportschau Live",
          "slug": "new-jersey-devils-vs-tampa-bay-lightning"
        },
        {
          "title": "New York Islanders vs Anaheim Ducks",
          "time": "01:00",
          "sender": "Sportschau Live",
          "slug": "new-york-islanders-vs-anaheim-ducks"
        }
      ]
    },
    {
      "title": "Toronto Maple Leafs vs San Jose Sharks",
      "time": "01:00",
      "iso_time": "",
      "sport": "Eishockey",
      "sport_slug": "eishockey",
      "sender": "Sportschau Live",
      "sender_slug": "sportschau-live",
      "link": "https://www.sportschau.de/live-und-ergebnisse/eishockey/nhl/ma11413742/toronto-maple-leafs_san-jose-sharks/info",
      "slug": "toronto-maple-leafs-vs-san-jose-sharks",
      "subtitle": "",
      "related_events": [
        {
          "title": "Columbus Blue Jackets vs Ottawa Senators",
          "time": "01:00",
          "sender": "Sportschau Live",
          "slug": "columbus-blue-jackets-vs-ottawa-senators"
        },
        {
          "title": "New Jersey Devils vs Tampa Bay Lightning",
          "time": "01:00",
          "sender": "Sportschau Live",
          "slug": "new-jersey-devils-vs-tampa-bay-lightning"
        },
        {
          "title": "New York Islanders vs Anaheim Ducks",
          "time": "01:00",
          "sender": "Sportschau Live",
          "slug": "new-york-islanders-vs-anaheim-ducks"
        }
      ]
    },
    {
      "title": "Washington Capitals vs Carolina Hurricanes",
      "time": "01:00",
      "iso_time": "",
      "sport": "Eishockey",
      "sport_slug": "eishockey",
      "sender": "Sportschau Live",
      "sender_slug": "sportschau-live",
      "link": "https://www.sportschau.de/live-und-ergebnisse/eishockey/nhl/ma11413745/washington-capitals_carolina-hurricanes/info",
      "slug": "washington-capitals-vs-carolina-hurricanes",
      "subtitle": "",
      "related_events": [
        {
          "title": "Columbus Blue Jackets vs Ottawa Senators",
          "time": "01:00",
          "sender": "Sportschau Live",
          "slug": "columbus-blue-jackets-vs-ottawa-senators"
        },
        {
          "title": "New Jersey Devils vs Tampa Bay Lightning",
          "time": "01:00",
          "sender": "Sportschau Live",
          "slug": "new-jersey-devils-vs-tampa-bay-lightning"
        },
        {
          "title": "New York Islanders vs Anaheim Ducks",
          "time": "01:00",
          "sender": "Sportschau Live",
          "slug": "new-york-islanders-vs-anaheim-ducks"
        }
      ]
    },
    {
      "title": "Minnesota Wild vs Dallas Stars",
      "time": "02:00",
      "iso_time": "",
      "sport": "Eishockey",
      "sport_slug": "eishockey",
      "sender": "Sportschau Live",
      "sender_slug": "sportschau-live",
      "link": "https://www.sportschau.de/live-und-ergebnisse/eishockey/nhl/ma11413748/minnesota-wild_dallas-stars/info",
      "slug": "minnesota-wild-vs-dallas-stars",
      "subtitle": "",
      "related_events": [
        {
          "title": "Nashville Predators vs St. Louis Blues",
          "time": "02:00",
          "sender": "Sportschau Live",
          "slug": "nashville-predators-vs-st-louis-blues"
        },
        {
          "title": "Winnipeg Jets vs Boston Bruins",
          "time": "02:00",
          "sender": "Sportschau Live",
          "slug": "winnipeg-jets-vs-boston-bruins"
        }
      ]
    },
    {
      "title": "Nashville Predators vs St. Louis Blues",
      "time": "02:00",
      "iso_time": "",
      "sport": "Eishockey",
      "sport_slug": "eishockey",
      "sender": "Sportschau Live",
      "sender_slug": "sportschau-live",
      "link": "https://www.sportschau.de/live-und-ergebnisse/eishockey/nhl/ma11413751/nashville-predators_st-louis-blues/info",
      "slug": "nashville-predators-vs-st-louis-blues",
      "subtitle": "",
      "related_events": [
        {
          "title": "Minnesota Wild vs Dallas Stars",
          "time": "02:00",
          "sender": "Sportschau Live",
          "slug": "minnesota-wild-vs-dallas-stars"
        },
        {
          "title": "Winnipeg Jets vs Boston Bruins",
          "time": "02:00",
          "sender": "Sportschau Live",
          "slug": "winnipeg-jets-vs-boston-bruins"
        }
      ]
    },
    {
      "title": "Winnipeg Jets vs Boston Bruins",
      "time": "02:00",
      "iso_time": "",
      "sport": "Eishockey",
      "sport_slug": "eishockey",
      "sender": "Sportschau Live",
      "sender_slug": "sportschau-live",
      "link": "https://www.sportschau.de/live-und-ergebnisse/eishockey/nhl/ma11413754/winnipeg-jets_boston-bruins/info",
      "slug": "winnipeg-jets-vs-boston-bruins",
      "subtitle": "",
      "related_events": [
        {
          "title": "Minnesota Wild vs Dallas Stars",
          "time": "02:00",
          "sender": "Sportschau Live",
          "slug": "minnesota-wild-vs-dallas-stars"
        },
        {
          "title": "Nashville Predators vs St. Louis Blues",
          "time": "02:00",
          "sender": "Sportschau Live",
          "slug": "nashville-predators-vs-st-louis-blues"
        }
      ]
    },
    {
      "title": "Edmonton Oilers vs Detroit Red Wings",
      "time": "03:00",
      "iso_time": "",
      "sport": "Eishockey",
      "sport_slug": "eishockey",
      "sender": "Sportschau Live",
      "sender_slug": "sportschau-live",
      "link": "https://www.sportschau.de/live-und-ergebnisse/eishockey/nhl/ma11413760/edmonton-oilers_detroit-red-wings/info",
      "slug": "edmonton-oilers-vs-detroit-red-wings",
      "subtitle": "",
      "related_events": []
    },
    {
      "title": "Colorado Avalanche vs Florida Panthers",
      "time": "03:30",
      "iso_time": "",
      "sport": "Eishockey",
      "sport_slug": "eishockey",
      "sender": "Sportschau Live",
      "sender_slug": "sportschau-live",
      "link": "https://www.sportschau.de/live-und-ergebnisse/eishockey/nhl/ma11413757/colorado-avalanche_florida-panthers/info",
      "slug": "colorado-avalanche-vs-florida-panthers",
      "subtitle": "",
      "related_events": []
    },
    {
      "title": "Vancouver Canucks vs Buffalo Sabres",
      "time": "04:00",
      "iso_time": "",
      "sport": "Eishockey",
      "sport_slug": "eishockey",
      "sender": "Sportschau Live",
      "sender_slug": "sportschau-live",
      "link": "https://www.sportschau.de/live-und-ergebnisse/eishockey/nhl/ma11413763/vancouver-canucks_buffalo-sabres/info",
      "slug": "vancouver-canucks-vs-buffalo-sabres",
      "subtitle": "",
      "related_events": []
    },
    {
      "title": "Tremblant | Riesenslalom | 2. Lauf",
      "subtitle": "Weltcup | Frauen",
      "sport": "Ski Alpin",
      "sport_slug": "ski-alpin",
      "sender": "Eurosport",
      "sender_slug": "eurosport",
      "time": "00:46",
      "iso_time": "2025-12-12T00:46:57+01:00",
      "link": "",
      "slug": "tremblant-riesenslalom-2-lauf",
      "related_events": [
        {
          "title": "Beaver Creek | Riesenslalom | 1. Lauf",
          "time": "01:58",
          "sender": "Eurosport",
          "slug": "beaver-creek-riesenslalom-1-lauf"
        },
        {
          "title": "Beaver Creek | Riesenslalom | 2. Lauf",
          "time": "02:37",
          "sender": "Eurosport",
          "slug": "beaver-creek-riesenslalom-2-lauf"
        },
        {
          "title": "Tremblant | Riesenslalom | 1. Lauf",
          "time": "03:00",
          "sender": "Eurosport",
          "slug": "tremblant-riesenslalom-1-lauf"
        }
      ]
    },
    {
      "title": "Wisla | Einzel | 1. Durchgang",
      "subtitle": "Weltcup | Männer | HS 134",
      "sport": "Skispringen",
      "sport_slug": "skispringen",
      "sender": "Eurosport",
      "sender_slug": "eurosport",
      "time": "00:55",
      "iso_time": "2025-12-12T00:55:52+01:00",
      "link": "",
      "slug": "wisla-einzel-1-durchgang",
      "related_events": [
        {
          "title": "Wisla | Einzel | 2. Durchgang",
          "time": "01:25",
          "sender": "Eurosport",
          "slug": "wisla-einzel-2-durchgang"
        }
      ]
    },
    {
      "title": "Wisla | Einzel | 2. Durchgang",
      "subtitle": "Weltcup | Männer | HS 134",
      "sport": "Skispringen",
      "sport_slug": "skispringen",
      "sender": "Eurosport",
      "sender_slug": "eurosport",
      "time": "01:25",
      "iso_time": "2025-12-12T01:25:45+01:00",
      "link": "",
      "slug": "wisla-einzel-2-durchgang",
      "related_events": [
        {
          "title": "Wisla | Einzel | 1. Durchgang",
          "time": "00:55",
          "sender": "Eurosport",
          "slug": "wisla-einzel-1-durchgang"
        }
      ]
    },
    {
      "title": "Beaver Creek | Riesenslalom | 1. Lauf",
      "subtitle": "Weltcup | Männer",
      "sport": "Ski Alpin",
      "sport_slug": "ski-alpin",
      "sender": "Eurosport",
      "sender_slug": "eurosport",
      "time": "01:58",
      "iso_time": "2025-12-12T01:58:25+01:00",
      "link": "",
      "slug": "beaver-creek-riesenslalom-1-lauf",
      "related_events": [
        {
          "title": "Tremblant | Riesenslalom | 2. Lauf",
          "time": "00:46",
          "sender": "Eurosport",
          "slug": "tremblant-riesenslalom-2-lauf"
        },
        {
          "title": "Beaver Creek | Riesenslalom | 2. Lauf",
          "time": "02:37",
          "sender": "Eurosport",
          "slug": "beaver-creek-riesenslalom-2-lauf"
        },
        {
          "title": "Tremblant | Riesenslalom | 1. Lauf",
          "time": "03:00",
          "sender": "Eurosport",
          "slug": "tremblant-riesenslalom-1-lauf"
        }
      ]
    },
    {
      "title": "Beaver Creek | Riesenslalom | 2. Lauf",
      "subtitle": "Weltcup | Männer",
      "sport": "Ski Alpin",
      "sport_slug": "ski-alpin",
      "sender": "Eurosport",
      "sender_slug": "eurosport",
      "time": "02:37",
      "iso_time": "2025-12-12T02:37:01+01:00",
      "link": "",
      "slug": "beaver-creek-riesenslalom-2-lauf",
      "related_events": [
        {
          "title": "Tremblant | Riesenslalom | 2. Lauf",
          "time": "00:46",
          "sender": "Eurosport",
          "slug": "tremblant-riesenslalom-2-lauf"
        },
        {
          "title": "Beaver Creek | Riesenslalom | 1. Lauf",
          "time": "01:58",
          "sender": "Eurosport",
          "slug": "beaver-creek-riesenslalom-1-lauf"
        },
        {
          "title": "Tremblant | Riesenslalom | 1. Lauf",
          "time": "03:00",
          "sender": "Eurosport",
          "slug": "tremblant-riesenslalom-1-lauf"
        }
      ]
    },
    {
      "title": "Tremblant | Riesenslalom | 1. Lauf",
      "subtitle": "Weltcup | Frauen",
      "sport": "Ski Alpin",
      "sport_slug": "ski-alpin",
      "sender": "Eurosport",
      "sender_slug": "eurosport",
      "time": "03:00",
      "iso_time": "2025-12-12T03:00:46+01:00",
      "link": "",
      "slug": "tremblant-riesenslalom-1-lauf",
      "related_events": [
        {
          "title": "Tremblant | Riesenslalom | 2. Lauf",
          "time": "00:46",
          "sender": "Eurosport",
          "slug": "tremblant-riesenslalom-2-lauf"
        },
        {
          "title": "Beaver Creek | Riesenslalom | 1. Lauf",
          "time": "01:58",
          "sender": "Eurosport",
          "slug": "beaver-creek-riesenslalom-1-lauf"
        },
        {
          "title": "Beaver Creek | Riesenslalom | 2. Lauf",
          "time": "02:37",
          "sender": "Eurosport",
          "slug": "beaver-creek-riesenslalom-2-lauf"
        }
      ]
    },
    {
      "title": "Tremblant | Riesenslalom | 2. Lauf",
      "subtitle": "Weltcup | Frauen",
      "sport": "Ski Alpin",
      "sport_slug": "ski-alpin",
      "sender": "Eurosport",
      "sender_slug": "eurosport",
      "time": "03:29",
      "iso_time": "2025-12-12T03:29:56+01:00",
      "link": "https://play.discoveryplus.com/video/watch/53103096-e821-5d72-bb0d-55508b7672e6?utm_source=universal_search",
      "slug": "tremblant-riesenslalom-2-lauf",
      "related_events": [
        {
          "title": "Beaver Creek | Riesenslalom | 1. Lauf",
          "time": "01:58",
          "sender": "Eurosport",
          "slug": "beaver-creek-riesenslalom-1-lauf"
        },
        {
          "title": "Beaver Creek | Riesenslalom | 2. Lauf",
          "time": "02:37",
          "sender": "Eurosport",
          "slug": "beaver-creek-riesenslalom-2-lauf"
        },
        {
          "title": "Tremblant | Riesenslalom | 1. Lauf",
          "time": "03:00",
          "sender": "Eurosport",
          "slug": "tremblant-riesenslalom-1-lauf"
        }
      ]
    },
    {
      "title": "Secret Garden | Halfpipe",
      "subtitle": "Weltcup | Frauen / Männer | Englischer Kommentar",
      "sport": "Snowboard",
      "sport_slug": "snowboard",
      "sender": "Eurosport",
      "sender_slug": "eurosport",
      "time": "03:50",
      "iso_time": "2025-12-12T03:50:00+01:00",
      "link": "https://play.discoveryplus.com/video/watch/6899073f-7882-5fc5-a193-29926af3fbef?utm_source=universal_search",
      "slug": "secret-garden-halfpipe",
      "related_events": []
    },
    {
      "title": "Shoot Out | 1. Runde",
      "subtitle": "Mit Hossein Vafaei u.a. | Blackpool | European Series",
      "sport": "Snooker",
      "sport_slug": "snooker",
      "sender": "Eurosport",
      "sender_slug": "eurosport",
      "time": "03:57",
      "iso_time": "2025-12-12T03:57:26+01:00",
      "link": "https://play.discoveryplus.com/video/watch/3623cb70-2f48-5317-9016-a77cbe51ae05?utm_source=universal_search",
      "slug": "shoot-out-1-runde",
      "related_events": []
    },
    {
      "title": "Val Thorens | Skicross",
      "subtitle": "Weltcup | Frauen / Männer",
      "sport": "Ski Freestyle",
      "sport_slug": "ski-freestyle",
      "sender": "Eurosport",
      "sender_slug": "eurosport",
      "time": "05:59",
      "iso_time": "2025-12-12T05:59:29+01:00",
      "link": "https://play.discoveryplus.com/video/watch/0afc833c-d0e9-52f1-9b31-c1b38d68f82c?utm_source=universal_search",
      "slug": "val-thorens-skicross",
      "related_events": []
    },
    {
      "title": "Dubai T100 | Highlights",
      "subtitle": "T100 Triathlon World Tour | Männer / Frauen",
      "sport": "Triathlon",
      "sport_slug": "triathlon",
      "sender": "Eurosport",
      "sender_slug": "eurosport",
      "time": "06:42",
      "iso_time": "2025-12-12T06:42:18+01:00",
      "link": "https://play.discoveryplus.com/video/watch/04159a51-c093-56fd-9a5c-d11fdd911747?utm_source=universal_search",
      "slug": "dubai-t100-highlights",
      "related_events": [
        {
          "title": "T100 Triathlon World Tour | Doha T100",
          "time": "07:45",
          "sender": "Eurosport",
          "slug": "t100-triathlon-world-tour-doha-t100"
        },
        {
          "title": "T100 Triathlon World Tour | Doha T100",
          "time": "07:45",
          "sender": "Eurosport",
          "slug": "t100-triathlon-world-tour-doha-t100"
        }
      ]
    },
    {
      "title": "T100 Triathlon World Tour | Doha T100",
      "subtitle": "Männer | 9. Station",
      "sport": "Triathlon",
      "sport_slug": "triathlon",
      "sender": "Eurosport",
      "sender_slug": "eurosport",
      "time": "07:45",
      "iso_time": "2025-12-12T07:45:00+01:00",
      "link": "https://play.discoveryplus.com/video/watch/c9c0fcb6-07e8-5b77-94a4-5a892ef1e1de?utm_source=universal_search",
      "slug": "t100-triathlon-world-tour-doha-t100",
      "related_events": [
        {
          "title": "Dubai T100 | Highlights",
          "time": "06:42",
          "sender": "Eurosport",
          "slug": "dubai-t100-highlights"
        }
      ]
    },
    {
      "title": "T100 Triathlon World Tour | Doha T100",
      "subtitle": "Männer | 9. Station",
      "sport": "Triathlon",
      "sport_slug": "triathlon",
      "sender": "Eurosport",
      "sender_slug": "eurosport",
      "time": "07:45",
      "iso_time": "2025-12-12T07:45:00+01:00",
      "link": "https://play.discoveryplus.com/video/watch/5289d1ce-1b12-524e-b58d-4eead3ab3702?utm_source=universal_search",
      "slug": "t100-triathlon-world-tour-doha-t100",
      "related_events": [
        {
          "title": "Dubai T100 | Highlights",
          "time": "06:42",
          "sender": "Eurosport",
          "slug": "dubai-t100-highlights"
        }
      ]
    },
    {
      "title": "Tremblant | Riesenslalom | 1. Lauf",
      "subtitle": "Weltcup | Frauen",
      "sport": "Ski Alpin",
      "sport_slug": "ski-alpin",
      "sender": "Eurosport",
      "sender_slug": "eurosport",
      "time": "08:36",
      "iso_time": "2025-12-12T08:36:07+01:00",
      "link": "https://play.discoveryplus.com/video/watch/3305dfd1-2525-57a6-8b2d-99310e8ea939?utm_source=universal_search",
      "slug": "tremblant-riesenslalom-1-lauf",
      "related_events": [
        {
          "title": "Tremblant | Riesenslalom | 2. Lauf",
          "time": "09:12",
          "sender": "Eurosport",
          "slug": "tremblant-riesenslalom-2-lauf"
        },
        {
          "title": "St. Moritz | Abfahrt",
          "time": "10:00",
          "sender": "Eurosport",
          "slug": "st-moritz-abfahrt"
        },
        {
          "title": "St. Moritz | Abfahrt",
          "time": "10:00",
          "sender": "Eurosport",
          "slug": "st-moritz-abfahrt"
        }
      ]
    },
    {
      "title": "Tremblant | Riesenslalom | 2. Lauf",
      "subtitle": "Weltcup | Frauen",
      "sport": "Ski Alpin",
      "sport_slug": "ski-alpin",
      "sender": "Eurosport",
      "sender_slug": "eurosport",
      "time": "09:12",
      "iso_time": "2025-12-12T09:12:50+01:00",
      "link": "https://play.discoveryplus.com/video/watch/c7420e20-e080-56a7-aaf2-8afee11d6008?utm_source=universal_search",
      "slug": "tremblant-riesenslalom-2-lauf",
      "related_events": [
        {
          "title": "Tremblant | Riesenslalom | 1. Lauf",
          "time": "08:36",
          "sender": "Eurosport",
          "slug": "tremblant-riesenslalom-1-lauf"
        },
        {
          "title": "St. Moritz | Abfahrt",
          "time": "10:00",
          "sender": "Eurosport",
          "slug": "st-moritz-abfahrt"
        },
        {
          "title": "St. Moritz | Abfahrt",
          "time": "10:00",
          "sender": "Eurosport",
          "slug": "st-moritz-abfahrt"
        }
      ]
    },
    {
      "title": "St. Moritz | Abfahrt",
      "subtitle": "Weltcup | Frauen",
      "sport": "Ski Alpin",
      "sport_slug": "ski-alpin",
      "sender": "Eurosport",
      "sender_slug": "eurosport",
      "time": "10:00",
      "iso_time": "2025-12-12T10:00:00+01:00",
      "link": "https://play.discoveryplus.com/video/watch/aa2c21ca-42f8-5dfe-a7f5-0cfce746505e?utm_source=universal_search",
      "slug": "st-moritz-abfahrt",
      "related_events": [
        {
          "title": "Tremblant | Riesenslalom | 1. Lauf",
          "time": "08:36",
          "sender": "Eurosport",
          "slug": "tremblant-riesenslalom-1-lauf"
        },
        {
          "title": "Tremblant | Riesenslalom | 2. Lauf",
          "time": "09:12",
          "sender": "Eurosport",
          "slug": "tremblant-riesenslalom-2-lauf"
        }
      ]
    },
    {
      "title": "St. Moritz | Abfahrt",
      "subtitle": "Weltcup | Frauen",
      "sport": "Ski Alpin",
      "sport_slug": "ski-alpin",
      "sender": "Eurosport",
      "sender_slug": "eurosport",
      "time": "10:00",
      "iso_time": "2025-12-12T10:00:00+01:00",
      "link": "https://play.discoveryplus.com/video/watch/c21d77d3-c1fb-5cf8-828c-ec65222d882b?utm_source=universal_search",
      "slug": "st-moritz-abfahrt",
      "related_events": [
        {
          "title": "Tremblant | Riesenslalom | 1. Lauf",
          "time": "08:36",
          "sender": "Eurosport",
          "slug": "tremblant-riesenslalom-1-lauf"
        },
        {
          "title": "Tremblant | Riesenslalom | 2. Lauf",
          "time": "09:12",
          "sender": "Eurosport",
          "slug": "tremblant-riesenslalom-2-lauf"
        }
      ]
    },
    {
      "title": "Hochfilzen | Sprint | Training",
      "subtitle": "Weltcup | Männer | Original Sound",
      "sport": "Biathlon",
      "sport_slug": "biathlon",
      "sender": "Eurosport",
      "sender_slug": "eurosport",
      "time": "10:25",
      "iso_time": "2025-12-12T10:25:00+01:00",
      "link": "https://play.discoveryplus.com/video/watch/cf6d1b7c-997f-524b-8d43-47a533a4dc4c?utm_source=universal_search",
      "slug": "hochfilzen-sprint-training",
      "related_events": [
        {
          "title": "Hochfilzen | 10km Sprint",
          "time": "11:10",
          "sender": "Eurosport",
          "slug": "hochfilzen-10km-sprint"
        },
        {
          "title": "Hochfilzen | Sprint | Zusatz-Feed",
          "time": "11:15",
          "sender": "Eurosport",
          "slug": "hochfilzen-sprint-zusatz-feed"
        },
        {
          "title": "Hochfilzen | Sprint | Schießstand",
          "time": "11:15",
          "sender": "Eurosport",
          "slug": "hochfilzen-sprint-schiessstand"
        }
      ]
    },
    {
      "title": "Hochfilzen | 10km Sprint",
      "subtitle": "Weltcup | Männer",
      "sport": "Biathlon",
      "sport_slug": "biathlon",
      "sender": "Eurosport",
      "sender_slug": "eurosport",
      "time": "11:10",
      "iso_time": "2025-12-12T11:10:00+01:00",
      "link": "https://play.discoveryplus.com/video/watch/cc7cf1f6-7e9f-5059-a96f-d2d04939d40c?utm_source=universal_search",
      "slug": "hochfilzen-10km-sprint",
      "related_events": [
        {
          "title": "Hochfilzen | Sprint | Training",
          "time": "10:25",
          "sender": "Eurosport",
          "slug": "hochfilzen-sprint-training"
        },
        {
          "title": "Hochfilzen | Sprint | Zusatz-Feed",
          "time": "11:15",
          "sender": "Eurosport",
          "slug": "hochfilzen-sprint-zusatz-feed"
        },
        {
          "title": "Hochfilzen | Sprint | Schießstand",
          "time": "11:15",
          "sender": "Eurosport",
          "slug": "hochfilzen-sprint-schiessstand"
        }
      ]
    },
    {
      "title": "Hochfilzen | Sprint | Zusatz-Feed",
      "subtitle": "Weltcup | Männer | Original Sound",
      "sport": "Biathlon",
      "sport_slug": "biathlon",
      "sender": "Eurosport",
      "sender_slug": "eurosport",
      "time": "11:15",
      "iso_time": "2025-12-12T11:15:00+01:00",
      "link": "https://play.discoveryplus.com/video/watch/2210465f-0172-5fbc-acc5-9ed622d0d749?utm_source=universal_search",
      "slug": "hochfilzen-sprint-zusatz-feed",
      "related_events": [
        {
          "title": "Hochfilzen | Sprint | Training",
          "time": "10:25",
          "sender": "Eurosport",
          "slug": "hochfilzen-sprint-training"
        },
        {
          "title": "Hochfilzen | 10km Sprint",
          "time": "11:10",
          "sender": "Eurosport",
          "slug": "hochfilzen-10km-sprint"
        },
        {
          "title": "Hochfilzen | Sprint | Schießstand",
          "time": "11:15",
          "sender": "Eurosport",
          "slug": "hochfilzen-sprint-schiessstand"
        }
      ]
    },
    {
      "title": "Hochfilzen | Sprint | Schießstand",
      "subtitle": "Weltcup | Männer | Original Sound",
      "sport": "Biathlon",
      "sport_slug": "biathlon",
      "sender": "Eurosport",
      "sender_slug": "eurosport",
      "time": "11:15",
      "iso_time": "2025-12-12T11:15:00+01:00",
      "link": "https://play.discoveryplus.com/video/watch/0bf96a10-dad2-5969-9860-49598c0dfe9c?utm_source=universal_search",
      "slug": "hochfilzen-sprint-schiessstand",
      "related_events": [
        {
          "title": "Hochfilzen | Sprint | Training",
          "time": "10:25",
          "sender": "Eurosport",
          "slug": "hochfilzen-sprint-training"
        },
        {
          "title": "Hochfilzen | 10km Sprint",
          "time": "11:10",
          "sender": "Eurosport",
          "slug": "hochfilzen-10km-sprint"
        },
        {
          "title": "Hochfilzen | Sprint | Zusatz-Feed",
          "time": "11:15",
          "sender": "Eurosport",
          "slug": "hochfilzen-sprint-zusatz-feed"
        }
      ]
    },
    {
      "title": "Hochfilzen | 10km Sprint",
      "subtitle": "Weltcup | Männer",
      "sport": "Biathlon",
      "sport_slug": "biathlon",
      "sender": "Eurosport",
      "sender_slug": "eurosport",
      "time": "11:45",
      "iso_time": "2025-12-12T11:45:00+01:00",
      "link": "https://play.discoveryplus.com/video/watch/5183513e-747f-52ec-9b4e-32dd48dd468e?utm_source=universal_search",
      "slug": "hochfilzen-10km-sprint",
      "related_events": [
        {
          "title": "Hochfilzen | Sprint | Training",
          "time": "10:25",
          "sender": "Eurosport",
          "slug": "hochfilzen-sprint-training"
        },
        {
          "title": "Hochfilzen | Sprint | Zusatz-Feed",
          "time": "11:15",
          "sender": "Eurosport",
          "slug": "hochfilzen-sprint-zusatz-feed"
        },
        {
          "title": "Hochfilzen | Sprint | Schießstand",
          "time": "11:15",
          "sender": "Eurosport",
          "slug": "hochfilzen-sprint-schiessstand"
        }
      ]
    },
    {
      "title": "Val Thorens | Skicross",
      "subtitle": "Weltcup | Frauen / Männer",
      "sport": "Ski Freestyle",
      "sport_slug": "ski-freestyle",
      "sender": "Eurosport",
      "sender_slug": "eurosport",
      "time": "12:20",
      "iso_time": "2025-12-12T12:20:00+01:00",
      "link": "https://play.discoveryplus.com/video/watch/93291631-62a0-5b9d-b296-72d4d47e4ae1?utm_source=universal_search",
      "slug": "val-thorens-skicross",
      "related_events": []
    },
    {
      "title": "Val Thorens | Skicross",
      "subtitle": "Weltcup | Frauen / Männer",
      "sport": "Ski Freestyle",
      "sport_slug": "ski-freestyle",
      "sender": "Eurosport",
      "sender_slug": "eurosport",
      "time": "12:45",
      "iso_time": "2025-12-12T12:45:00+01:00",
      "link": "https://play.discoveryplus.com/video/watch/34fec717-443a-51c0-b155-ec062026e165?utm_source=universal_search",
      "slug": "val-thorens-skicross",
      "related_events": []
    },
    {
      "title": "Hochfilzen | Sprint | Training",
      "subtitle": "Weltcup | Frauen | Original Sound",
      "sport": "Biathlon",
      "sport_slug": "biathlon",
      "sender": "Eurosport",
      "sender_slug": "eurosport",
      "time": "13:15",
      "iso_time": "2025-12-12T13:15:00+01:00",
      "link": "https://play.discoveryplus.com/video/watch/4dc3eb7a-815c-53ce-bc6e-1d4e67cfffb6?utm_source=universal_search",
      "slug": "hochfilzen-sprint-training",
      "related_events": [
        {
          "title": "Hochfilzen | 10km Sprint",
          "time": "11:10",
          "sender": "Eurosport",
          "slug": "hochfilzen-10km-sprint"
        },
        {
          "title": "Hochfilzen | Sprint | Zusatz-Feed",
          "time": "11:15",
          "sender": "Eurosport",
          "slug": "hochfilzen-sprint-zusatz-feed"
        },
        {
          "title": "Hochfilzen | Sprint | Schießstand",
          "time": "11:15",
          "sender": "Eurosport",
          "slug": "hochfilzen-sprint-schiessstand"
        }
      ]
    },
    {
      "title": "Shoot Out | 2. Runde",
      "subtitle": "Mit Jackson Page u.a. | Blackpool | European Series",
      "sport": "Snooker",
      "sport_slug": "snooker",
      "sender": "Eurosport",
      "sender_slug": "eurosport",
      "time": "14:00",
      "iso_time": "2025-12-12T14:00:00+01:00",
      "link": "https://play.discoveryplus.com/video/watch/d83b65d9-f5c4-5d61-b3f0-38b40f3b9bca?utm_source=universal_search",
      "slug": "shoot-out-2-runde",
      "related_events": []
    },
    {
      "title": "Hochfilzen | 7,5km Sprint",
      "subtitle": "Weltcup | Frauen",
      "sport": "Biathlon",
      "sport_slug": "biathlon",
      "sender": "Eurosport",
      "sender_slug": "eurosport",
      "time": "14:00",
      "iso_time": "2025-12-12T14:00:00+01:00",
      "link": "https://play.discoveryplus.com/video/watch/41c9edc5-608e-56b2-96b2-1fbebcd79cfc?utm_source=universal_search",
      "slug": "hochfilzen-75km-sprint",
      "related_events": [
        {
          "title": "Hochfilzen | 10km Sprint",
          "time": "11:10",
          "sender": "Eurosport",
          "slug": "hochfilzen-10km-sprint"
        },
        {
          "title": "Hochfilzen | Sprint | Zusatz-Feed",
          "time": "11:15",
          "sender": "Eurosport",
          "slug": "hochfilzen-sprint-zusatz-feed"
        },
        {
          "title": "Hochfilzen | Sprint | Schießstand",
          "time": "11:15",
          "sender": "Eurosport",
          "slug": "hochfilzen-sprint-schiessstand"
        }
      ]
    },
    {
      "title": "Hochfilzen | 7,5km Sprint",
      "subtitle": "Weltcup | Frauen",
      "sport": "Biathlon",
      "sport_slug": "biathlon",
      "sender": "Eurosport",
      "sender_slug": "eurosport",
      "time": "14:00",
      "iso_time": "2025-12-12T14:00:00+01:00",
      "link": "https://play.discoveryplus.com/video/watch/20dc41b3-64f2-557c-bf79-f09d5f6e9132?utm_source=universal_search",
      "slug": "hochfilzen-75km-sprint",
      "related_events": [
        {
          "title": "Hochfilzen | 10km Sprint",
          "time": "11:10",
          "sender": "Eurosport",
          "slug": "hochfilzen-10km-sprint"
        },
        {
          "title": "Hochfilzen | Sprint | Zusatz-Feed",
          "time": "11:15",
          "sender": "Eurosport",
          "slug": "hochfilzen-sprint-zusatz-feed"
        },
        {
          "title": "Hochfilzen | Sprint | Schießstand",
          "time": "11:15",
          "sender": "Eurosport",
          "slug": "hochfilzen-sprint-schiessstand"
        }
      ]
    },
    {
      "title": "Hochfilzen | Sprint | Schießstand",
      "subtitle": "Weltcup | Frauen | Original Sound",
      "sport": "Biathlon",
      "sport_slug": "biathlon",
      "sender": "Eurosport",
      "sender_slug": "eurosport",
      "time": "14:05",
      "iso_time": "2025-12-12T14:05:00+01:00",
      "link": "https://play.discoveryplus.com/video/watch/3e80601f-c2ad-5210-ba68-443180308fe9?utm_source=universal_search",
      "slug": "hochfilzen-sprint-schiessstand",
      "related_events": [
        {
          "title": "Hochfilzen | 10km Sprint",
          "time": "11:10",
          "sender": "Eurosport",
          "slug": "hochfilzen-10km-sprint"
        },
        {
          "title": "Hochfilzen | Sprint | Zusatz-Feed",
          "time": "11:15",
          "sender": "Eurosport",
          "slug": "hochfilzen-sprint-zusatz-feed"
        },
        {
          "title": "Hochfilzen | 10km Sprint",
          "time": "11:45",
          "sender": "Eurosport",
          "slug": "hochfilzen-10km-sprint"
        }
      ]
    },
    {
      "title": "Hochfilzen | Sprint | Zusatz-Feed",
      "subtitle": "Weltcup | Frauen | Original Sound",
      "sport": "Biathlon",
      "sport_slug": "biathlon",
      "sender": "Eurosport",
      "sender_slug": "eurosport",
      "time": "14:05",
      "iso_time": "2025-12-12T14:05:00+01:00",
      "link": "https://play.discoveryplus.com/video/watch/9068a151-6d59-5ffb-84f3-33af70d4b717?utm_source=universal_search",
      "slug": "hochfilzen-sprint-zusatz-feed",
      "related_events": [
        {
          "title": "Hochfilzen | 10km Sprint",
          "time": "11:10",
          "sender": "Eurosport",
          "slug": "hochfilzen-10km-sprint"
        },
        {
          "title": "Hochfilzen | Sprint | Schießstand",
          "time": "11:15",
          "sender": "Eurosport",
          "slug": "hochfilzen-sprint-schiessstand"
        },
        {
          "title": "Hochfilzen | 10km Sprint",
          "time": "11:45",
          "sender": "Eurosport",
          "slug": "hochfilzen-10km-sprint"
        }
      ]
    },
    {
      "title": "Hochfilzen | 7,5km Sprint",
      "subtitle": "Weltcup | Frauen",
      "sport": "Biathlon",
      "sport_slug": "biathlon",
      "sender": "Eurosport",
      "sender_slug": "eurosport",
      "time": "14:15",
      "iso_time": "2025-12-12T14:15:00+01:00",
      "link": "https://play.discoveryplus.com/video/watch/e190a222-102b-5306-92e7-3a248aa80953?utm_source=universal_search",
      "slug": "hochfilzen-75km-sprint",
      "related_events": [
        {
          "title": " vs ",
          "time": "14:15",
          "sender": "Sportschau Live",
          "slug": "vs"
        },
        {
          "title": "Hochfilzen | Sprint | Zusatz-Feed",
          "time": "11:15",
          "sender": "Eurosport",
          "slug": "hochfilzen-sprint-zusatz-feed"
        },
        {
          "title": "Hochfilzen | Sprint | Schießstand",
          "time": "11:15",
          "sender": "Eurosport",
          "slug": "hochfilzen-sprint-schiessstand"
        }
      ]
    },
    {
      "title": "Davos | Freistil-Teamsprint | Qualifikation",
      "subtitle": "Weltcup | Frauen / Männer | Englischer Kommentar",
      "sport": "Skilanglauf",
      "sport_slug": "skilanglauf",
      "sender": "Eurosport",
      "sender_slug": "eurosport",
      "time": "14:55",
      "iso_time": "2025-12-12T14:55:00+01:00",
      "link": "https://play.discoveryplus.com/video/watch/e88af3e4-d86e-5400-afed-d652fd805f15?utm_source=universal_search",
      "slug": "davos-freistil-teamsprint-qualifikation",
      "related_events": [
        {
          "title": "Davos | Freistil-Teamsprint",
          "time": "16:50",
          "sender": "Eurosport",
          "slug": "davos-freistil-teamsprint"
        },
        {
          "title": "Davos | Freistil-Teamsprint",
          "time": "17:05",
          "sender": "Eurosport",
          "slug": "davos-freistil-teamsprint"
        }
      ]
    },
    {
      "title": "Klingenthal | Einzelspringen",
      "subtitle": "Weltcup | Frauen | HS 140",
      "sport": "Skispringen",
      "sport_slug": "skispringen",
      "sender": "Eurosport",
      "sender_slug": "eurosport",
      "time": "15:25",
      "iso_time": "2025-12-12T15:25:00+01:00",
      "link": "https://play.discoveryplus.com/video/watch/d6bf505d-e2f4-511d-9247-687b3f62ccbc?utm_source=universal_search",
      "slug": "klingenthal-einzelspringen",
      "related_events": []
    },
    {
      "title": "Shoot Out | 2. Runde",
      "subtitle": "Mit Lei Peifan u.a. | Blackpool | European Series",
      "sport": "Snooker",
      "sport_slug": "snooker",
      "sender": "Eurosport",
      "sender_slug": "eurosport",
      "time": "15:35",
      "iso_time": "2025-12-12T15:35:00+01:00",
      "link": "https://play.discoveryplus.com/video/watch/0dc27bbc-6482-5419-a417-13e7ffed0fdb?utm_source=universal_search",
      "slug": "shoot-out-2-runde",
      "related_events": []
    },
    {
      "title": "Klingenthal | Einzelspringen",
      "subtitle": "Weltcup | Frauen | HS 140",
      "sport": "Skispringen",
      "sport_slug": "skispringen",
      "sender": "Eurosport",
      "sender_slug": "eurosport",
      "time": "15:35",
      "iso_time": "2025-12-12T15:35:00+01:00",
      "link": "https://play.discoveryplus.com/video/watch/1f4900c6-7f42-5680-894e-aa38b4d77937?utm_source=universal_search",
      "slug": "klingenthal-einzelspringen",
      "related_events": [
        {
          "title": " vs ",
          "time": "15:35",
          "sender": "Sportschau Live",
          "slug": "vs"
        }
      ]
    },
    {
      "title": "Davos | Freistil-Teamsprint",
      "subtitle": "Weltcup | Frauen / Männer",
      "sport": "Skilanglauf",
      "sport_slug": "skilanglauf",
      "sender": "Eurosport",
      "sender_slug": "eurosport",
      "time": "16:50",
      "iso_time": "2025-12-12T16:50:00+01:00",
      "link": "https://play.discoveryplus.com/video/watch/272465b4-8682-5bd2-8494-fc0603dab611?utm_source=universal_search",
      "slug": "davos-freistil-teamsprint",
      "related_events": [
        {
          "title": "Davos | Freistil-Teamsprint | Qualifikation",
          "time": "14:55",
          "sender": "Eurosport",
          "slug": "davos-freistil-teamsprint-qualifikation"
        }
      ]
    },
    {
      "title": "Davos | Freistil-Teamsprint",
      "subtitle": "Weltcup | Männer / Frauen",
      "sport": "Skilanglauf",
      "sport_slug": "skilanglauf",
      "sender": "Eurosport",
      "sender_slug": "eurosport",
      "time": "17:05",
      "iso_time": "2025-12-12T17:05:00+01:00",
      "link": "https://play.discoveryplus.com/video/watch/3cb0a255-2e40-5cca-a9b0-5028848b7d08?utm_source=universal_search",
      "slug": "davos-freistil-teamsprint",
      "related_events": [
        {
          "title": "Davos | Freistil-Teamsprint | Qualifikation",
          "time": "14:55",
          "sender": "Eurosport",
          "slug": "davos-freistil-teamsprint-qualifikation"
        }
      ]
    },
    {
      "title": "St. Moritz | Abfahrt",
      "subtitle": "Weltcup | Frauen",
      "sport": "Ski Alpin",
      "sport_slug": "ski-alpin",
      "sender": "Eurosport",
      "sender_slug": "eurosport",
      "time": "17:55",
      "iso_time": "2025-12-12T17:55:00+01:00",
      "link": "https://play.discoveryplus.com/video/watch/27565cb8-3b0e-52ca-9025-8e1e42227b8e?utm_source=universal_search",
      "slug": "st-moritz-abfahrt",
      "related_events": []
    },
    {
      "title": "Hochfilzen | 10km Sprint",
      "subtitle": "Weltcup | Männer",
      "sport": "Biathlon",
      "sport_slug": "biathlon",
      "sender": "Eurosport",
      "sender_slug": "eurosport",
      "time": "18:00",
      "iso_time": "2025-12-12T18:00:00+01:00",
      "link": "https://play.discoveryplus.com/video/watch/c262a295-75f2-5d6a-acbf-de343339a205?utm_source=universal_search",
      "slug": "hochfilzen-10km-sprint",
      "related_events": [
        {
          "title": "Hochfilzen | 7,5km Sprint",
          "time": "18:45",
          "sender": "Eurosport",
          "slug": "hochfilzen-75km-sprint"
        },
        {
          "title": "Hochfilzen | 7,5km Sprint",
          "time": "21:00",
          "sender": "Eurosport",
          "slug": "hochfilzen-75km-sprint"
        }
      ]
    },
    {
      "title": "Hamar | Tag 1",
      "subtitle": "Weltcup | 4. Station | Englischer Kommentar",
      "sport": "Eisschnelllauf",
      "sport_slug": "eisschnelllauf",
      "sender": "Eurosport",
      "sender_slug": "eurosport",
      "time": "18:25",
      "iso_time": "2025-12-12T18:25:00+01:00",
      "link": "https://play.discoveryplus.com/video/watch/89c5089a-b610-5617-81e5-29e65536d38b?utm_source=universal_search",
      "slug": "hamar-tag-1",
      "related_events": []
    },
    {
      "title": "Hochfilzen | 7,5km Sprint",
      "subtitle": "Weltcup | Frauen",
      "sport": "Biathlon",
      "sport_slug": "biathlon",
      "sender": "Eurosport",
      "sender_slug": "eurosport",
      "time": "18:45",
      "iso_time": "2025-12-12T18:45:00+01:00",
      "link": "https://play.discoveryplus.com/video/watch/37c17bbe-6665-5331-93e1-ea1602661d0b?utm_source=universal_search",
      "slug": "hochfilzen-75km-sprint",
      "related_events": [
        {
          "title": "Hochfilzen | 10km Sprint",
          "time": "18:00",
          "sender": "Eurosport",
          "slug": "hochfilzen-10km-sprint"
        },
        {
          "title": "Hochfilzen | 10km Sprint",
          "time": "20:00",
          "sender": "Eurosport",
          "slug": "hochfilzen-10km-sprint"
        }
      ]
    },
    {
      "title": "Val Thorens | Skicross",
      "subtitle": "Weltcup | Frauen / Männer",
      "sport": "Ski Freestyle",
      "sport_slug": "ski-freestyle",
      "sender": "Eurosport",
      "sender_slug": "eurosport",
      "time": "19:00",
      "iso_time": "2025-12-12T19:00:00+01:00",
      "link": "https://play.discoveryplus.com/video/watch/b1bb737c-aa26-5624-8003-ead3930879cb?utm_source=universal_search",
      "slug": "val-thorens-skicross",
      "related_events": []
    },
    {
      "title": "Klingenthal | Qualifikation",
      "subtitle": "Weltcup | Männer | HS 140",
      "sport": "Skispringen",
      "sport_slug": "skispringen",
      "sender": "Eurosport",
      "sender_slug": "eurosport",
      "time": "19:25",
      "iso_time": "2025-12-12T19:25:00+01:00",
      "link": "https://play.discoveryplus.com/video/watch/3266586c-e70d-5eea-8add-cd4e06987176?utm_source=universal_search",
      "slug": "klingenthal-qualifikation",
      "related_events": []
    },
    {
      "title": "Klingenthal | Qualifikation",
      "subtitle": "Weltcup | Männer | HS 140",
      "sport": "Skispringen",
      "sport_slug": "skispringen",
      "sender": "Eurosport",
      "sender_slug": "eurosport",
      "time": "19:25",
      "iso_time": "2025-12-12T19:25:00+01:00",
      "link": "https://play.discoveryplus.com/video/watch/fbd6b3f0-616e-5451-b3e4-13ca9f550965?utm_source=universal_search",
      "slug": "klingenthal-qualifikation",
      "related_events": []
    },
    {
      "title": "Shoot Out | 2. Runde",
      "subtitle": "Mit Stuart Bingham u.a. | Blackpool | European Series",
      "sport": "Snooker",
      "sport_slug": "snooker",
      "sender": "Eurosport",
      "sender_slug": "eurosport",
      "time": "19:45",
      "iso_time": "2025-12-12T19:45:00+01:00",
      "link": "https://play.discoveryplus.com/video/watch/6b5d9895-28e5-5e5e-b676-58c456fd8944?utm_source=universal_search",
      "slug": "shoot-out-2-runde",
      "related_events": []
    },
    {
      "title": "Hochfilzen | 10km Sprint",
      "subtitle": "Weltcup | Männer",
      "sport": "Biathlon",
      "sport_slug": "biathlon",
      "sender": "Eurosport",
      "sender_slug": "eurosport",
      "time": "20:00",
      "iso_time": "2025-12-12T20:00:00+01:00",
      "link": "https://play.discoveryplus.com/video/watch/f6dbe7ef-96d8-55a9-8ed5-12d1aa5505ef?utm_source=universal_search",
      "slug": "hochfilzen-10km-sprint",
      "related_events": [
        {
          "title": "Hochfilzen | 7,5km Sprint",
          "time": "18:45",
          "sender": "Eurosport",
          "slug": "hochfilzen-75km-sprint"
        },
        {
          "title": "Hochfilzen | 7,5km Sprint",
          "time": "21:00",
          "sender": "Eurosport",
          "slug": "hochfilzen-75km-sprint"
        }
      ]
    },
    {
      "title": "Shoot Out | 2. Runde",
      "subtitle": "Mit Stuart BIngham u.a. | Blackpool | European Series",
      "sport": "Snooker",
      "sport_slug": "snooker",
      "sender": "Eurosport",
      "sender_slug": "eurosport",
      "time": "20:30",
      "iso_time": "2025-12-12T20:30:00+01:00",
      "link": "https://play.discoveryplus.com/video/watch/e86c96f8-bb32-5b4d-8df8-c543c72a4e1a?utm_source=universal_search",
      "slug": "shoot-out-2-runde",
      "related_events": []
    },
    {
      "title": "Hochfilzen | 7,5km Sprint",
      "subtitle": "Weltcup | Frauen",
      "sport": "Biathlon",
      "sport_slug": "biathlon",
      "sender": "Eurosport",
      "sender_slug": "eurosport",
      "time": "21:00",
      "iso_time": "2025-12-12T21:00:00+01:00",
      "link": "https://play.discoveryplus.com/video/watch/a89c0c8a-1bf9-51d4-a890-088e09561a0f?utm_source=universal_search",
      "slug": "hochfilzen-75km-sprint",
      "related_events": [
        {
          "title": "Hochfilzen | 10km Sprint",
          "time": "18:00",
          "sender": "Eurosport",
          "slug": "hochfilzen-10km-sprint"
        },
        {
          "title": "Hochfilzen | 10km Sprint",
          "time": "20:00",
          "sender": "Eurosport",
          "slug": "hochfilzen-10km-sprint"
        }
      ]
    },
    {
      "title": "St. Moritz | Abfahrt",
      "subtitle": "Weltcup | Frauen",
      "sport": "Ski Alpin",
      "sport_slug": "ski-alpin",
      "sender": "Eurosport",
      "sender_slug": "eurosport",
      "time": "22:00",
      "iso_time": "2025-12-12T22:00:00+01:00",
      "link": "https://play.discoveryplus.com/video/watch/687b137c-6dd9-5c65-b58f-5b2ec9952e4f?utm_source=universal_search",
      "slug": "st-moritz-abfahrt",
      "related_events": []
    },
    {
      "title": "Weltcup | La Coruña | Highlights",
      "subtitle": "Springreiten | Western European League",
      "sport": "Reitsport",
      "sport_slug": "reitsport",
      "sender": "Eurosport",
      "sender_slug": "eurosport",
      "time": "23:00",
      "iso_time": "2025-12-12T23:00:00+01:00",
      "link": "https://play.discoveryplus.com/video/watch/3a1d9e08-e930-51a3-9a64-e0f437210c76?utm_source=universal_search",
      "slug": "weltcup-la-coruna-highlights",
      "related_events": []
    },
    {
      "title": "T100 Triathlon World Tour | Doha T100",
      "subtitle": "Männer | 9. Station",
      "sport": "Triathlon",
      "sport_slug": "triathlon",
      "sender": "Eurosport",
      "sender_slug": "eurosport",
      "time": "00:00",
      "iso_time": "2025-12-13T00:00:00+01:00",
      "link": "https://play.discoveryplus.com/video/watch/4e9bcb6a-327f-5d46-9fdb-89b3377f6623?utm_source=universal_search",
      "slug": "t100-triathlon-world-tour-doha-t100",
      "related_events": []
    },
    {
      "title": "WM | Frankreich - Deutschland",
      "subtitle": "Halbfinale | Rotterdam",
      "sport": "Handball",
      "sport_slug": "handball",
      "sender": "Eurosport",
      "sender_slug": "eurosport",
      "time": "00:00",
      "iso_time": "2025-12-13T00:00:00+01:00",
      "link": "https://play.discoveryplus.com/video/watch/bbfbf8b3-6f46-5f28-9e37-77fc420b8622?utm_source=universal_search",
      "slug": "wm-frankreich-deutschland",
      "related_events": []
    },
    {
      "title": "Shoot Out | 2. Runde",
      "subtitle": "Mit Stuart BIngham u.a. | Blackpool | European Series",
      "sport": "Snooker",
      "sport_slug": "snooker",
      "sender": "Eurosport",
      "sender_slug": "eurosport",
      "time": "01:00",
      "iso_time": "2025-12-13T01:00:00+01:00",
      "link": "https://play.discoveryplus.com/video/watch/25ce7f69-c953-536c-8f31-386934ac5719?utm_source=universal_search",
      "slug": "shoot-out-2-runde",
      "related_events": []
    }
  ]
}