{
  "date": "2026-04-29",
  "events": [
    {
      "title": "Atlético Madrid vs Arsenal FC",
      "time": "21:00",
      "iso_time": "",
      "sport": "Fußball",
      "sport_slug": "fussball",
      "sender": "Sportschau Live",
      "sender_slug": "sportschau-live",
      "link": "https://www.sportschau.de/live-und-ergebnisse/fussball/uefa-champions-league/ma11584304/atletico-madrid_arsenal-fc/info",
      "slug": "atletico-madrid-vs-arsenal-fc",
      "subtitle": "",
      "related_events": []
    },
    {
      "title": "Werder Bremen vs Bayern München",
      "time": "18:00",
      "iso_time": "",
      "sport": "Fußball",
      "sport_slug": "fussball",
      "sender": "Sportschau Live",
      "sender_slug": "sportschau-live",
      "link": "https://www.sportschau.de/live-und-ergebnisse/fussball/deutschland-bundesliga-frauen/ma11376146/werder-bremen_bayern-muenchen/info",
      "slug": "werder-bremen-vs-bayern-munchen",
      "subtitle": "",
      "related_events": []
    },
    {
      "title": "FC Nantes vs OL Lyonnes",
      "time": "19:00",
      "iso_time": "",
      "sport": "Fußball",
      "sport_slug": "fussball",
      "sender": "Sportschau Live",
      "sender_slug": "sportschau-live",
      "link": "https://www.sportschau.de/live-und-ergebnisse/fussball/frankreich-frauen-division-1/ma11397290/fc-nantes_ol-lyonnes/info",
      "slug": "fc-nantes-vs-ol-lyonnes",
      "subtitle": "",
      "related_events": []
    },
    {
      "title": "Arsenal WFC vs Leicester City WFC",
      "time": "20:00",
      "iso_time": "",
      "sport": "Fußball",
      "sport_slug": "fussball",
      "sender": "Sportschau Live",
      "sender_slug": "sportschau-live",
      "link": "https://www.sportschau.de/live-und-ergebnisse/fussball/england-womens-super-league/ma11454065/arsenal-wfc_leicester-city-wfc/info",
      "slug": "arsenal-wfc-vs-leicester-city-wfc",
      "subtitle": "",
      "related_events": []
    },
    {
      "title": "SC Pick Szeged vs SC Magdeburg",
      "time": "18:45",
      "iso_time": "",
      "sport": "Handball",
      "sport_slug": "handball",
      "sender": "Sportschau Live",
      "sender_slug": "sportschau-live",
      "link": "https://www.sportschau.de/live-und-ergebnisse/handball/ehf-champions-league/ma11942474/sc-pick-szeged_sc-magdeburg/info",
      "slug": "sc-pick-szeged-vs-sc-magdeburg",
      "subtitle": "",
      "related_events": [
        {
          "title": "Sporting CP vs Aalborg Håndbold",
          "time": "18:45",
          "sender": "Sportschau Live",
          "slug": "sporting-cp-vs-aalborg-handbold"
        }
      ]
    },
    {
      "title": "Sporting CP vs Aalborg Håndbold",
      "time": "18:45",
      "iso_time": "",
      "sport": "Handball",
      "sport_slug": "handball",
      "sender": "Sportschau Live",
      "sender_slug": "sportschau-live",
      "link": "https://www.sportschau.de/live-und-ergebnisse/handball/ehf-champions-league/ma11942480/sporting-cp_aalborg-handbold/info",
      "slug": "sporting-cp-vs-aalborg-handbold",
      "subtitle": "",
      "related_events": [
        {
          "title": "SC Pick Szeged vs SC Magdeburg",
          "time": "18:45",
          "sender": "Sportschau Live",
          "slug": "sc-pick-szeged-vs-sc-magdeburg"
        }
      ]
    },
    {
      "title": "SG Flensburg-Handewitt vs TSV Hannover-Burgdorf",
      "time": "20:45",
      "iso_time": "",
      "sport": "Handball",
      "sport_slug": "handball",
      "sender": "Sportschau Live",
      "sender_slug": "sportschau-live",
      "link": "https://www.sportschau.de/live-und-ergebnisse/handball/ehf-european-league/ma11975191/sg-flensburg-handewitt_tsv-hannover-burgdorf/info",
      "slug": "sg-flensburg-handewitt-vs-tsv-hannover-burgdorf",
      "subtitle": "",
      "related_events": []
    },
    {
      "title": "Real Madrid vs Hapoel Tel Aviv",
      "time": "20:45",
      "iso_time": "",
      "sport": "Basketball",
      "sport_slug": "basketball",
      "sender": "Sportschau Live",
      "sender_slug": "sportschau-live",
      "link": "https://www.sportschau.de/live-und-ergebnisse/basketball/euroleague-basketball/ma12000584/real-madrid_hapoel-tel-aviv/info",
      "slug": "real-madrid-vs-hapoel-tel-aviv",
      "subtitle": "",
      "related_events": []
    },
    {
      "title": "Sporting CP vs CD Tondela",
      "time": "21:15",
      "iso_time": "",
      "sport": "Fußball",
      "sport_slug": "fussball",
      "sender": "Sportschau Live",
      "sender_slug": "sportschau-live",
      "link": "https://www.sportschau.de/live-und-ergebnisse/fussball/portugal-primeira-liga/ma11306009/sporting-cp_cd-tondela/info",
      "slug": "sporting-cp-vs-cd-tondela",
      "subtitle": "",
      "related_events": []
    },
    {
      "title": "Boston Celtics vs Philadelphia 76ers",
      "time": "01:00",
      "iso_time": "",
      "sport": "Basketball",
      "sport_slug": "basketball",
      "sender": "Sportschau Live",
      "sender_slug": "sportschau-live",
      "link": "https://www.sportschau.de/live-und-ergebnisse/basketball/usa-nba/ma12005405/boston-celtics_philadelphia-76ers/info",
      "slug": "boston-celtics-vs-philadelphia-76ers",
      "subtitle": "",
      "related_events": []
    },
    {
      "title": "New York Knicks vs Atlanta Hawks",
      "time": "02:00",
      "iso_time": "",
      "sport": "Basketball",
      "sport_slug": "basketball",
      "sender": "Sportschau Live",
      "sender_slug": "sportschau-live",
      "link": "https://www.sportschau.de/live-und-ergebnisse/basketball/usa-nba/ma12004244/new-york-knicks_atlanta-hawks/info",
      "slug": "new-york-knicks-vs-atlanta-hawks",
      "subtitle": "",
      "related_events": []
    },
    {
      "title": "San Antonio Spurs vs Portland Trail Blazers",
      "time": "03:30",
      "iso_time": "",
      "sport": "Basketball",
      "sport_slug": "basketball",
      "sender": "Sportschau Live",
      "sender_slug": "sportschau-live",
      "link": "https://www.sportschau.de/live-und-ergebnisse/basketball/usa-nba/ma12005408/san-antonio-spurs_portland-trail-blazers/info",
      "slug": "san-antonio-spurs-vs-portland-trail-blazers",
      "subtitle": "",
      "related_events": []
    },
    {
      "title": "Buffalo Sabres vs Boston Bruins",
      "time": "01:30",
      "iso_time": "",
      "sport": "Eishockey",
      "sport_slug": "eishockey",
      "sender": "Sportschau Live",
      "sender_slug": "sportschau-live",
      "link": "https://www.sportschau.de/live-und-ergebnisse/eishockey/nhl/ma12005360/buffalo-sabres_boston-bruins/info",
      "slug": "buffalo-sabres-vs-boston-bruins",
      "subtitle": "",
      "related_events": []
    },
    {
      "title": "Dallas Stars vs Minnesota Wild",
      "time": "02:00",
      "iso_time": "",
      "sport": "Eishockey",
      "sport_slug": "eishockey",
      "sender": "Sportschau Live",
      "sender_slug": "sportschau-live",
      "link": "https://www.sportschau.de/live-und-ergebnisse/eishockey/nhl/ma12003887/dallas-stars_minnesota-wild/info",
      "slug": "dallas-stars-vs-minnesota-wild",
      "subtitle": "",
      "related_events": []
    },
    {
      "title": "Edmonton Oilers vs Anaheim Ducks",
      "time": "04:00",
      "iso_time": "",
      "sport": "Eishockey",
      "sport_slug": "eishockey",
      "sender": "Sportschau Live",
      "sender_slug": "sportschau-live",
      "link": "https://www.sportschau.de/live-und-ergebnisse/eishockey/nhl/ma12006314/edmonton-oilers_anaheim-ducks/info",
      "slug": "edmonton-oilers-vs-anaheim-ducks",
      "subtitle": "",
      "related_events": []
    },
    {
      "title": "Karolina Plíšková vs Anastasia Potapova",
      "time": "13:00",
      "iso_time": "",
      "sport": "Tennis",
      "sport_slug": "tennis",
      "sender": "Sportschau Live",
      "sender_slug": "sportschau-live",
      "link": "https://www.sportschau.de/live-und-ergebnisse/tennis/wta-spanien-mutua-madrilena-madrid-open/ma11778544/karolina-pliskova_anastasia-potapova/info",
      "slug": "karolina-pliskova-vs-anastasia-potapova",
      "subtitle": "",
      "related_events": []
    },
    {
      "title": "Marta Kostyuk vs Linda Noskova",
      "time": "20:00",
      "iso_time": "",
      "sport": "Tennis",
      "sport_slug": "tennis",
      "sender": "Sportschau Live",
      "sender_slug": "sportschau-live",
      "link": "https://www.sportschau.de/live-und-ergebnisse/tennis/wta-spanien-mutua-madrilena-madrid-open/ma11778541/marta-kostyuk_linda-noskova/info",
      "slug": "marta-kostyuk-vs-linda-noskova",
      "subtitle": "",
      "related_events": []
    },
    {
      "title": "Jannik Sinner vs Rafael Jodar",
      "time": "16:00",
      "iso_time": "",
      "sport": "Tennis",
      "sport_slug": "tennis",
      "sender": "Sportschau Live",
      "sender_slug": "sportschau-live",
      "link": "https://www.sportschau.de/live-und-ergebnisse/tennis/atp-spanien-mutua-madrilena-madrid-open/ma11752528/jannik-sinner_rafael-jodar/info",
      "slug": "jannik-sinner-vs-rafael-jodar",
      "subtitle": "",
      "related_events": []
    },
    {
      "title": "Arthur Fils vs Jiří Lehečka",
      "time": "21:30",
      "iso_time": "",
      "sport": "Tennis",
      "sport_slug": "tennis",
      "sender": "Sportschau Live",
      "sender_slug": "sportschau-live",
      "link": "https://www.sportschau.de/live-und-ergebnisse/tennis/atp-spanien-mutua-madrilena-madrid-open/ma11752531/arthur-fils_jiri-lehecka/info",
      "slug": "arthur-fils-vs-jiri-lehecka",
      "subtitle": "",
      "related_events": []
    },
    {
      "title": "Tour de Romandie | Prolog",
      "subtitle": "UCI World Tour | Männer | Villars-sur-Glâne - Villars-sur-Glâne (3,2km / EZF)",
      "sport": "Radsport",
      "sport_slug": "radsport",
      "sender": "Eurosport",
      "sender_slug": "eurosport",
      "time": "01:29",
      "iso_time": "2026-04-29T01:29:58+02:00",
      "link": "",
      "slug": "tour-de-romandie-prolog",
      "related_events": [
        {
          "title": "Türkei-Rundfahrt | 3. Etappe",
          "time": "04:29",
          "sender": "Eurosport",
          "slug": "turkei-rundfahrt-3-etappe"
        }
      ]
    },
    {
      "title": "WM | Viertelfinale",
      "subtitle": "Mit Zhao X. - S. Murphy u.a. | Sheffield",
      "sport": "Snooker",
      "sport_slug": "snooker",
      "sender": "Eurosport",
      "sender_slug": "eurosport",
      "time": "02:30",
      "iso_time": "2026-04-29T02:30:18+02:00",
      "link": "",
      "slug": "wm-viertelfinale",
      "related_events": []
    },
    {
      "title": "Türkei-Rundfahrt | 3. Etappe",
      "subtitle": "UCI Pro Series | Männer | Marmaris - Kıran (132,7km)",
      "sport": "Radsport",
      "sport_slug": "radsport",
      "sender": "Eurosport",
      "sender_slug": "eurosport",
      "time": "04:29",
      "iso_time": "2026-04-29T04:29:30+02:00",
      "link": "",
      "slug": "turkei-rundfahrt-3-etappe",
      "related_events": [
        {
          "title": "Tour de Romandie | Prolog",
          "time": "01:29",
          "sender": "Eurosport",
          "slug": "tour-de-romandie-prolog"
        },
        {
          "title": "Tour de Romandie | Prolog",
          "time": "05:27",
          "sender": "Eurosport",
          "slug": "tour-de-romandie-prolog"
        }
      ]
    },
    {
      "title": "Tour de Romandie | Prolog",
      "subtitle": "UCI World Tour | Männer | Villars-sur-Glâne - Villars-sur-Glâne (3,2km / EZF)",
      "sport": "Radsport",
      "sport_slug": "radsport",
      "sender": "Eurosport",
      "sender_slug": "eurosport",
      "time": "05:27",
      "iso_time": "2026-04-29T05:27:56+02:00",
      "link": "",
      "slug": "tour-de-romandie-prolog",
      "related_events": [
        {
          "title": "Türkei-Rundfahrt | 3. Etappe",
          "time": "04:29",
          "sender": "Eurosport",
          "slug": "turkei-rundfahrt-3-etappe"
        }
      ]
    },
    {
      "title": "WM | Viertelfinale",
      "subtitle": "Mit Zhao X. - S. Murphy u.a. | Sheffield",
      "sport": "Snooker",
      "sport_slug": "snooker",
      "sender": "Eurosport",
      "sender_slug": "eurosport",
      "time": "06:27",
      "iso_time": "2026-04-29T06:27:13+02:00",
      "link": "https://play.hbomax.com/sport/61ca79cb-e454-5424-a8b7-b3b0b4de5f90?utm_source=wbd_eurosport_web&utm_campaign=sportsEditorial-program-redirection&utm_medium=owned&utm_content=programsByDate_Program_url",
      "slug": "wm-viertelfinale",
      "related_events": []
    },
    {
      "title": "Australian Open | Finale | Herren-Einzel",
      "subtitle": "Carlos Alcaraz - Novak Djokovic | Melbourne",
      "sport": "Tennis",
      "sport_slug": "tennis",
      "sender": "Eurosport",
      "sender_slug": "eurosport",
      "time": "08:30",
      "iso_time": "2026-04-29T08:30:03+02:00",
      "link": "https://play.hbomax.com/sport/9ce3154a-929a-57a4-9d3c-56d3baa3c6f6?utm_source=wbd_eurosport_web&utm_campaign=sportsEditorial-program-redirection&utm_medium=owned&utm_content=programsByDate_Program_url",
      "slug": "australian-open-finale-herren-einzel",
      "related_events": []
    },
    {
      "title": "Tour de Romandie | Prolog",
      "subtitle": "UCI World Tour | Männer | Villars-sur-Glâne - Villars-sur-Glâne (3,2km / EZF)",
      "sport": "Radsport",
      "sport_slug": "radsport",
      "sender": "Eurosport",
      "sender_slug": "eurosport",
      "time": "08:35",
      "iso_time": "2026-04-29T08:35:24+02:00",
      "link": "https://play.hbomax.com/sport/8cd4bbe2-0549-53a8-9b56-90316bf78d68?utm_source=wbd_eurosport_web&utm_campaign=sportsEditorial-program-redirection&utm_medium=owned&utm_content=programsByDate_Program_url",
      "slug": "tour-de-romandie-prolog",
      "related_events": [
        {
          "title": "Türkei-Rundfahrt | 3. Etappe",
          "time": "11:30",
          "sender": "Eurosport",
          "slug": "turkei-rundfahrt-3-etappe"
        }
      ]
    },
    {
      "title": "WM | Viertelfinale",
      "subtitle": "Mit Zhao X. - S. Murphy u.a. | Sheffield",
      "sport": "Snooker",
      "sport_slug": "snooker",
      "sender": "Eurosport",
      "sender_slug": "eurosport",
      "time": "09:34",
      "iso_time": "2026-04-29T09:34:16+02:00",
      "link": "https://play.hbomax.com/sport/d40dfb8d-d7e6-5409-943a-1ea189926df3?utm_source=wbd_eurosport_web&utm_campaign=sportsEditorial-program-redirection&utm_medium=owned&utm_content=programsByDate_Program_url",
      "slug": "wm-viertelfinale",
      "related_events": [
        {
          "title": "WM | Mark Allen - Barry Hawkins",
          "time": "11:00",
          "sender": "Eurosport",
          "slug": "wm-mark-allen-barry-hawkins"
        },
        {
          "title": "WM | John Higgins - Neil Robertson",
          "time": "11:00",
          "sender": "Eurosport",
          "slug": "wm-john-higgins-neil-robertson"
        }
      ]
    },
    {
      "title": "Tour de Romandie | Prolog",
      "subtitle": "UCI World Tour | Männer | Villars-sur-Glâne - Villars-sur-Glâne (3,2km / EZF)",
      "sport": "Radsport",
      "sport_slug": "radsport",
      "sender": "Eurosport",
      "sender_slug": "eurosport",
      "time": "10:30",
      "iso_time": "2026-04-29T10:30:03+02:00",
      "link": "https://play.hbomax.com/sport/4d68e89c-de67-5f3d-82da-bd167b13c6e3?utm_source=wbd_eurosport_web&utm_campaign=sportsEditorial-program-redirection&utm_medium=owned&utm_content=programsByDate_Program_url",
      "slug": "tour-de-romandie-prolog",
      "related_events": [
        {
          "title": "Türkei-Rundfahrt | 3. Etappe",
          "time": "11:30",
          "sender": "Eurosport",
          "slug": "turkei-rundfahrt-3-etappe"
        },
        {
          "title": "Türkei-Rundfahrt | 4. Etappe",
          "time": "13:30",
          "sender": "Eurosport",
          "slug": "turkei-rundfahrt-4-etappe"
        },
        {
          "title": "Türkei-Rundfahrt | 4. Etappe",
          "time": "13:30",
          "sender": "Eurosport",
          "slug": "turkei-rundfahrt-4-etappe"
        }
      ]
    },
    {
      "title": "WM | Mark Allen - Barry Hawkins",
      "subtitle": "Sheffield | Viertelfinale | 3. Session | Englischer Kommentar",
      "sport": "Snooker",
      "sport_slug": "snooker",
      "sender": "Eurosport",
      "sender_slug": "eurosport",
      "time": "11:00",
      "iso_time": "2026-04-29T11:00:00+02:00",
      "link": "https://play.hbomax.com/sport/c58544ac-16e8-5c1a-8829-fcacf6a52e21?utm_source=wbd_eurosport_web&utm_campaign=sportsEditorial-program-redirection&utm_medium=owned&utm_content=programsByDate_Program_url",
      "slug": "wm-mark-allen-barry-hawkins",
      "related_events": [
        {
          "title": "WM | Viertelfinale",
          "time": "09:34",
          "sender": "Eurosport",
          "slug": "wm-viertelfinale"
        },
        {
          "title": "WM | John Higgins - Neil Robertson",
          "time": "11:00",
          "sender": "Eurosport",
          "slug": "wm-john-higgins-neil-robertson"
        },
        {
          "title": "WM | Viertelfinale",
          "time": "11:00",
          "sender": "Eurosport",
          "slug": "wm-viertelfinale"
        }
      ]
    },
    {
      "title": "WM | John Higgins - Neil Robertson",
      "subtitle": "Sheffield | Viertelfinale | 2. Session",
      "sport": "Snooker",
      "sport_slug": "snooker",
      "sender": "Eurosport",
      "sender_slug": "eurosport",
      "time": "11:00",
      "iso_time": "2026-04-29T11:00:00+02:00",
      "link": "https://play.hbomax.com/sport/d9219adf-a5cf-50fe-a9d5-88677df3fd1c?utm_source=wbd_eurosport_web&utm_campaign=sportsEditorial-program-redirection&utm_medium=owned&utm_content=programsByDate_Program_url",
      "slug": "wm-john-higgins-neil-robertson",
      "related_events": [
        {
          "title": "WM | Viertelfinale",
          "time": "09:34",
          "sender": "Eurosport",
          "slug": "wm-viertelfinale"
        },
        {
          "title": "WM | Mark Allen - Barry Hawkins",
          "time": "11:00",
          "sender": "Eurosport",
          "slug": "wm-mark-allen-barry-hawkins"
        },
        {
          "title": "WM | Viertelfinale",
          "time": "11:00",
          "sender": "Eurosport",
          "slug": "wm-viertelfinale"
        }
      ]
    },
    {
      "title": "WM | Viertelfinale",
      "subtitle": "Mit J. Higgins - N. Robertson | Sheffield | 2. Session",
      "sport": "Snooker",
      "sport_slug": "snooker",
      "sender": "Eurosport",
      "sender_slug": "eurosport",
      "time": "11:00",
      "iso_time": "2026-04-29T11:00:00+02:00",
      "link": "https://play.hbomax.com/sport/d5f72ba6-bbf7-5c41-8aaa-ca82156d2ec3?utm_source=wbd_eurosport_web&utm_campaign=sportsEditorial-program-redirection&utm_medium=owned&utm_content=programsByDate_Program_url",
      "slug": "wm-viertelfinale",
      "related_events": [
        {
          "title": "WM | Mark Allen - Barry Hawkins",
          "time": "11:00",
          "sender": "Eurosport",
          "slug": "wm-mark-allen-barry-hawkins"
        },
        {
          "title": "WM | John Higgins - Neil Robertson",
          "time": "11:00",
          "sender": "Eurosport",
          "slug": "wm-john-higgins-neil-robertson"
        }
      ]
    },
    {
      "title": "Türkei-Rundfahrt | 3. Etappe",
      "subtitle": "UCI Pro Series | Männer | Marmaris - Kıran (132,7km)",
      "sport": "Radsport",
      "sport_slug": "radsport",
      "sender": "Eurosport",
      "sender_slug": "eurosport",
      "time": "11:30",
      "iso_time": "2026-04-29T11:30:06+02:00",
      "link": "https://play.hbomax.com/sport/1e13842b-9622-55df-be75-097d4b91862a?utm_source=wbd_eurosport_web&utm_campaign=sportsEditorial-program-redirection&utm_medium=owned&utm_content=programsByDate_Program_url",
      "slug": "turkei-rundfahrt-3-etappe",
      "related_events": [
        {
          "title": "Tour de Romandie | Prolog",
          "time": "08:35",
          "sender": "Eurosport",
          "slug": "tour-de-romandie-prolog"
        },
        {
          "title": "Tour de Romandie | Prolog",
          "time": "10:30",
          "sender": "Eurosport",
          "slug": "tour-de-romandie-prolog"
        },
        {
          "title": "Türkei-Rundfahrt | 4. Etappe",
          "time": "13:30",
          "sender": "Eurosport",
          "slug": "turkei-rundfahrt-4-etappe"
        }
      ]
    },
    {
      "title": "Race Bikes",
      "subtitle": "Mountainbike-Magazin | Folge 4",
      "sport": "Mountainbike",
      "sport_slug": "mountainbike",
      "sender": "Eurosport",
      "sender_slug": "eurosport",
      "time": "12:59",
      "iso_time": "2026-04-29T12:59:41+02:00",
      "link": "https://play.hbomax.com/sports?utm_campaign=sportsEditorial-program-redirection&utm_source=wbd_eurosport_web&utm_medium=owned&utm_content=programsByDate_Program_url",
      "slug": "race-bikes",
      "related_events": []
    },
    {
      "title": "Türkei-Rundfahrt | 4. Etappe",
      "subtitle": "UCI Pro Series | Männer | Marmaris - Fethiye (130,4km)",
      "sport": "Radsport",
      "sport_slug": "radsport",
      "sender": "Eurosport",
      "sender_slug": "eurosport",
      "time": "13:30",
      "iso_time": "2026-04-29T13:30:00+02:00",
      "link": "https://play.hbomax.com/sport/9cdbc12b-2928-5263-aeb0-ee75bfe7143d?utm_source=wbd_eurosport_web&utm_campaign=sportsEditorial-program-redirection&utm_medium=owned&utm_content=programsByDate_Program_url",
      "slug": "turkei-rundfahrt-4-etappe",
      "related_events": [
        {
          "title": "Tour de Romandie | Prolog",
          "time": "10:30",
          "sender": "Eurosport",
          "slug": "tour-de-romandie-prolog"
        },
        {
          "title": "Türkei-Rundfahrt | 3. Etappe",
          "time": "11:30",
          "sender": "Eurosport",
          "slug": "turkei-rundfahrt-3-etappe"
        },
        {
          "title": "Tour de Romandie | 1. Etappe",
          "time": "15:30",
          "sender": "Eurosport",
          "slug": "tour-de-romandie-1-etappe"
        }
      ]
    },
    {
      "title": "Türkei-Rundfahrt | 4. Etappe",
      "subtitle": "UCI Pro Series | Männer | Marmaris - Fethiye (130,4km)",
      "sport": "Radsport",
      "sport_slug": "radsport",
      "sender": "Eurosport",
      "sender_slug": "eurosport",
      "time": "13:30",
      "iso_time": "2026-04-29T13:30:00+02:00",
      "link": "https://play.hbomax.com/sport/b52e5fff-40bc-5f01-934b-d006c2f3cac1?utm_source=wbd_eurosport_web&utm_campaign=sportsEditorial-program-redirection&utm_medium=owned&utm_content=programsByDate_Program_url",
      "slug": "turkei-rundfahrt-4-etappe",
      "related_events": [
        {
          "title": "Tour de Romandie | Prolog",
          "time": "10:30",
          "sender": "Eurosport",
          "slug": "tour-de-romandie-prolog"
        },
        {
          "title": "Türkei-Rundfahrt | 3. Etappe",
          "time": "11:30",
          "sender": "Eurosport",
          "slug": "turkei-rundfahrt-3-etappe"
        },
        {
          "title": "Tour de Romandie | 1. Etappe",
          "time": "15:30",
          "sender": "Eurosport",
          "slug": "tour-de-romandie-1-etappe"
        }
      ]
    },
    {
      "title": "Australian Open | Finale | Damen-Einzel",
      "subtitle": "A. Sabalenka - E. Rybakina | Melbourne",
      "sport": "Tennis",
      "sport_slug": "tennis",
      "sender": "Eurosport",
      "sender_slug": "eurosport",
      "time": "14:00",
      "iso_time": "2026-04-29T14:00:00+02:00",
      "link": "https://play.hbomax.com/sport/0519e197-79fc-521a-9d4f-3cb6c80569f5?utm_source=wbd_eurosport_web&utm_campaign=sportsEditorial-program-redirection&utm_medium=owned&utm_content=programsByDate_Program_url",
      "slug": "australian-open-finale-damen-einzel",
      "related_events": []
    },
    {
      "title": "WM | Zhao Xintong - Shaun Murphy",
      "subtitle": "Sheffield | Viertelfinale | 3. Session",
      "sport": "Snooker",
      "sport_slug": "snooker",
      "sender": "Eurosport",
      "sender_slug": "eurosport",
      "time": "15:15",
      "iso_time": "2026-04-29T15:15:00+02:00",
      "link": "https://play.hbomax.com/sport/1d12b0fd-2357-5454-8d55-c462e3f14a1a?utm_source=wbd_eurosport_web&utm_campaign=sportsEditorial-program-redirection&utm_medium=owned&utm_content=programsByDate_Program_url",
      "slug": "wm-zhao-xintong-shaun-murphy",
      "related_events": [
        {
          "title": "WM | Viertelfinale",
          "time": "15:15",
          "sender": "Eurosport",
          "slug": "wm-viertelfinale"
        },
        {
          "title": "WM | Wu Yize - Hossein Vafaei",
          "time": "15:30",
          "sender": "Eurosport",
          "slug": "wm-wu-yize-hossein-vafaei"
        }
      ]
    },
    {
      "title": "WM | Viertelfinale",
      "subtitle": "Mit Zhao X. - S. Murphy u.a. | Sheffield | 3. Session",
      "sport": "Snooker",
      "sport_slug": "snooker",
      "sender": "Eurosport",
      "sender_slug": "eurosport",
      "time": "15:15",
      "iso_time": "2026-04-29T15:15:00+02:00",
      "link": "https://play.hbomax.com/sport/cae1346b-0d50-5054-8a51-4b5b459640f1?utm_source=wbd_eurosport_web&utm_campaign=sportsEditorial-program-redirection&utm_medium=owned&utm_content=programsByDate_Program_url",
      "slug": "wm-viertelfinale",
      "related_events": [
        {
          "title": "WM | Zhao Xintong - Shaun Murphy",
          "time": "15:15",
          "sender": "Eurosport",
          "slug": "wm-zhao-xintong-shaun-murphy"
        },
        {
          "title": "WM | Wu Yize - Hossein Vafaei",
          "time": "15:30",
          "sender": "Eurosport",
          "slug": "wm-wu-yize-hossein-vafaei"
        }
      ]
    },
    {
      "title": "WM | Wu Yize - Hossein Vafaei",
      "subtitle": "Sheffield | Viertelfinale | 2. Session | Englischer Kommentar",
      "sport": "Snooker",
      "sport_slug": "snooker",
      "sender": "Eurosport",
      "sender_slug": "eurosport",
      "time": "15:30",
      "iso_time": "2026-04-29T15:30:00+02:00",
      "link": "https://play.hbomax.com/sport/812f2363-df95-5084-bdd8-9d60eb34251f?utm_source=wbd_eurosport_web&utm_campaign=sportsEditorial-program-redirection&utm_medium=owned&utm_content=programsByDate_Program_url",
      "slug": "wm-wu-yize-hossein-vafaei",
      "related_events": [
        {
          "title": "WM | Zhao Xintong - Shaun Murphy",
          "time": "15:15",
          "sender": "Eurosport",
          "slug": "wm-zhao-xintong-shaun-murphy"
        },
        {
          "title": "WM | Viertelfinale",
          "time": "15:15",
          "sender": "Eurosport",
          "slug": "wm-viertelfinale"
        }
      ]
    },
    {
      "title": "Tour de Romandie | 1. Etappe",
      "subtitle": "UCI World Tour | Männer | Martigny - Martigny (171,2km)",
      "sport": "Radsport",
      "sport_slug": "radsport",
      "sender": "Eurosport",
      "sender_slug": "eurosport",
      "time": "15:30",
      "iso_time": "2026-04-29T15:30:00+02:00",
      "link": "https://play.hbomax.com/sport/4fafbc41-c475-5082-bca1-5409f09f922e?utm_source=wbd_eurosport_web&utm_campaign=sportsEditorial-program-redirection&utm_medium=owned&utm_content=programsByDate_Program_url",
      "slug": "tour-de-romandie-1-etappe",
      "related_events": [
        {
          "title": "Türkei-Rundfahrt | 4. Etappe",
          "time": "13:30",
          "sender": "Eurosport",
          "slug": "turkei-rundfahrt-4-etappe"
        },
        {
          "title": "Türkei-Rundfahrt | 4. Etappe",
          "time": "13:30",
          "sender": "Eurosport",
          "slug": "turkei-rundfahrt-4-etappe"
        },
        {
          "title": "The Cycling Show | FDJ United - Suez",
          "time": "17:45",
          "sender": "Eurosport",
          "slug": "the-cycling-show-fdj-united-suez"
        }
      ]
    },
    {
      "title": "Tour de Romandie | 1. Etappe",
      "subtitle": "UCI World Tour | Männer | Martigny - Martigny (171,2km)",
      "sport": "Radsport",
      "sport_slug": "radsport",
      "sender": "Eurosport",
      "sender_slug": "eurosport",
      "time": "15:30",
      "iso_time": "2026-04-29T15:30:00+02:00",
      "link": "https://play.hbomax.com/sport/6e76953b-6a20-553a-8ed3-076f068a2cde?utm_source=wbd_eurosport_web&utm_campaign=sportsEditorial-program-redirection&utm_medium=owned&utm_content=programsByDate_Program_url",
      "slug": "tour-de-romandie-1-etappe",
      "related_events": [
        {
          "title": "Türkei-Rundfahrt | 4. Etappe",
          "time": "13:30",
          "sender": "Eurosport",
          "slug": "turkei-rundfahrt-4-etappe"
        },
        {
          "title": "Türkei-Rundfahrt | 4. Etappe",
          "time": "13:30",
          "sender": "Eurosport",
          "slug": "turkei-rundfahrt-4-etappe"
        },
        {
          "title": "The Cycling Show | FDJ United - Suez",
          "time": "17:45",
          "sender": "Eurosport",
          "slug": "the-cycling-show-fdj-united-suez"
        }
      ]
    },
    {
      "title": "The Cycling Show | FDJ United - Suez",
      "subtitle": "Radsport-Magazin | Saison 2026 | Folge 5",
      "sport": "Radsport",
      "sport_slug": "radsport",
      "sender": "Eurosport",
      "sender_slug": "eurosport",
      "time": "17:45",
      "iso_time": "2026-04-29T17:45:00+02:00",
      "link": "https://play.hbomax.com/sports?utm_campaign=sportsEditorial-program-redirection&utm_source=wbd_eurosport_web&utm_medium=owned&utm_content=programsByDate_Program_url",
      "slug": "the-cycling-show-fdj-united-suez",
      "related_events": [
        {
          "title": "Tour de Romandie | 1. Etappe",
          "time": "15:30",
          "sender": "Eurosport",
          "slug": "tour-de-romandie-1-etappe"
        },
        {
          "title": "Tour de Romandie | 1. Etappe",
          "time": "15:30",
          "sender": "Eurosport",
          "slug": "tour-de-romandie-1-etappe"
        },
        {
          "title": "Türkei-Rundfahrt | 4. Etappe",
          "time": "18:15",
          "sender": "Eurosport",
          "slug": "turkei-rundfahrt-4-etappe"
        }
      ]
    },
    {
      "title": "Türkei-Rundfahrt | 4. Etappe",
      "subtitle": "UCI Pro Series | Männer | Marmaris - Fethiye (130,4km)",
      "sport": "Radsport",
      "sport_slug": "radsport",
      "sender": "Eurosport",
      "sender_slug": "eurosport",
      "time": "18:15",
      "iso_time": "2026-04-29T18:15:00+02:00",
      "link": "https://play.hbomax.com/sport/678ff812-0836-5b0a-ab1a-c810fc6ebcbf?utm_source=wbd_eurosport_web&utm_campaign=sportsEditorial-program-redirection&utm_medium=owned&utm_content=programsByDate_Program_url",
      "slug": "turkei-rundfahrt-4-etappe",
      "related_events": [
        {
          "title": "Tour de Romandie | 1. Etappe",
          "time": "15:30",
          "sender": "Eurosport",
          "slug": "tour-de-romandie-1-etappe"
        },
        {
          "title": "Tour de Romandie | 1. Etappe",
          "time": "15:30",
          "sender": "Eurosport",
          "slug": "tour-de-romandie-1-etappe"
        },
        {
          "title": "The Cycling Show | FDJ United - Suez",
          "time": "17:45",
          "sender": "Eurosport",
          "slug": "the-cycling-show-fdj-united-suez"
        }
      ]
    },
    {
      "title": "Australian Open | Finale | Herren-Einzel",
      "subtitle": "Carlos Alcaraz - Novak Djokovic | Melbourne",
      "sport": "Tennis",
      "sport_slug": "tennis",
      "sender": "Eurosport",
      "sender_slug": "eurosport",
      "time": "18:30",
      "iso_time": "2026-04-29T18:30:00+02:00",
      "link": "https://play.hbomax.com/sport/e9b83590-ef3a-566f-8932-11c4492efbbc?utm_source=wbd_eurosport_web&utm_campaign=sportsEditorial-program-redirection&utm_medium=owned&utm_content=programsByDate_Program_url",
      "slug": "australian-open-finale-herren-einzel",
      "related_events": []
    },
    {
      "title": "WM | John Higgins - Neil Robertson",
      "subtitle": "Sheffield | Viertelfinale | 3. Session",
      "sport": "Snooker",
      "sport_slug": "snooker",
      "sender": "Eurosport",
      "sender_slug": "eurosport",
      "time": "19:30",
      "iso_time": "2026-04-29T19:30:00+02:00",
      "link": "https://play.hbomax.com/sport/0bdea324-0bba-5017-be92-d9bf1e840294?utm_source=wbd_eurosport_web&utm_campaign=sportsEditorial-program-redirection&utm_medium=owned&utm_content=programsByDate_Program_url",
      "slug": "wm-john-higgins-neil-robertson",
      "related_events": [
        {
          "title": "WM | Viertelfinale",
          "time": "19:30",
          "sender": "Eurosport",
          "slug": "wm-viertelfinale"
        },
        {
          "title": "WM | Wu Yize - Hossein Vafaei",
          "time": "20:00",
          "sender": "Eurosport",
          "slug": "wm-wu-yize-hossein-vafaei"
        }
      ]
    },
    {
      "title": "WM | Viertelfinale",
      "subtitle": "Mit J. Higgins - N. Robertson | Sheffield | 3. Session",
      "sport": "Snooker",
      "sport_slug": "snooker",
      "sender": "Eurosport",
      "sender_slug": "eurosport",
      "time": "19:30",
      "iso_time": "2026-04-29T19:30:00+02:00",
      "link": "https://play.hbomax.com/sport/cbbc71cc-da3c-5041-8bba-9fbe091e54dc?utm_source=wbd_eurosport_web&utm_campaign=sportsEditorial-program-redirection&utm_medium=owned&utm_content=programsByDate_Program_url",
      "slug": "wm-viertelfinale",
      "related_events": [
        {
          "title": "WM | John Higgins - Neil Robertson",
          "time": "19:30",
          "sender": "Eurosport",
          "slug": "wm-john-higgins-neil-robertson"
        },
        {
          "title": "WM | Wu Yize - Hossein Vafaei",
          "time": "20:00",
          "sender": "Eurosport",
          "slug": "wm-wu-yize-hossein-vafaei"
        }
      ]
    },
    {
      "title": "Tour de Romandie | 1. Etappe",
      "subtitle": "UCI World Tour | Männer | Martigny - Martigny (171,2km)",
      "sport": "Radsport",
      "sport_slug": "radsport",
      "sender": "Eurosport",
      "sender_slug": "eurosport",
      "time": "19:30",
      "iso_time": "2026-04-29T19:30:00+02:00",
      "link": "https://play.hbomax.com/sport/166471d3-3f1e-577f-9b3d-5a9700b76929?utm_source=wbd_eurosport_web&utm_campaign=sportsEditorial-program-redirection&utm_medium=owned&utm_content=programsByDate_Program_url",
      "slug": "tour-de-romandie-1-etappe",
      "related_events": [
        {
          "title": "The Cycling Show | FDJ United - Suez",
          "time": "17:45",
          "sender": "Eurosport",
          "slug": "the-cycling-show-fdj-united-suez"
        },
        {
          "title": "Türkei-Rundfahrt | 4. Etappe",
          "time": "18:15",
          "sender": "Eurosport",
          "slug": "turkei-rundfahrt-4-etappe"
        }
      ]
    },
    {
      "title": "WM | Wu Yize - Hossein Vafaei",
      "subtitle": "Sheffield | Viertelfinale | 3. Session | Englischer Kommentar",
      "sport": "Snooker",
      "sport_slug": "snooker",
      "sender": "Eurosport",
      "sender_slug": "eurosport",
      "time": "20:00",
      "iso_time": "2026-04-29T20:00:00+02:00",
      "link": "https://play.hbomax.com/sport/c7996064-d76e-5e05-9588-d2273f813021?utm_source=wbd_eurosport_web&utm_campaign=sportsEditorial-program-redirection&utm_medium=owned&utm_content=programsByDate_Program_url",
      "slug": "wm-wu-yize-hossein-vafaei",
      "related_events": [
        {
          "title": "WM | John Higgins - Neil Robertson",
          "time": "19:30",
          "sender": "Eurosport",
          "slug": "wm-john-higgins-neil-robertson"
        },
        {
          "title": "WM | Viertelfinale",
          "time": "19:30",
          "sender": "Eurosport",
          "slug": "wm-viertelfinale"
        },
        {
          "title": "WM | Viertelfinale",
          "time": "23:00",
          "sender": "Eurosport",
          "slug": "wm-viertelfinale"
        }
      ]
    },
    {
      "title": "24h von Le Mans | Rennen",
      "subtitle": "FIM EWC | 1. Station",
      "sport": "Motorrad-Langstrecke",
      "sport_slug": "motorrad-langstrecke",
      "sender": "Eurosport",
      "sender_slug": "eurosport",
      "time": "20:30",
      "iso_time": "2026-04-29T20:30:00+02:00",
      "link": "https://play.hbomax.com/sport/0517dbea-fc57-56f3-a892-152ac9c64df3?utm_source=wbd_eurosport_web&utm_campaign=sportsEditorial-program-redirection&utm_medium=owned&utm_content=programsByDate_Program_url",
      "slug": "24h-von-le-mans-rennen",
      "related_events": []
    },
    {
      "title": "Discovery Golf",
      "subtitle": "Golf-Magazin",
      "sport": "Golf",
      "sport_slug": "golf",
      "sender": "Eurosport",
      "sender_slug": "eurosport",
      "time": "22:00",
      "iso_time": "2026-04-29T22:00:00+02:00",
      "link": "https://play.hbomax.com/sports?utm_campaign=sportsEditorial-program-redirection&utm_source=wbd_eurosport_web&utm_medium=owned&utm_content=programsByDate_Program_url",
      "slug": "discovery-golf",
      "related_events": []
    },
    {
      "title": "Tour de Romandie | 1. Etappe",
      "subtitle": "UCI World Tour | Männer | Martigny - Martigny (171,2km)",
      "sport": "Radsport",
      "sport_slug": "radsport",
      "sender": "Eurosport",
      "sender_slug": "eurosport",
      "time": "22:30",
      "iso_time": "2026-04-29T22:30:00+02:00",
      "link": "https://play.hbomax.com/sport/4daba995-e164-5257-927d-f6ac5ee9729b?utm_source=wbd_eurosport_web&utm_campaign=sportsEditorial-program-redirection&utm_medium=owned&utm_content=programsByDate_Program_url",
      "slug": "tour-de-romandie-1-etappe",
      "related_events": []
    },
    {
      "title": "WM | Viertelfinale",
      "subtitle": "Mit Zhao X. - S. Murphy u.a. | Sheffield | 3. Session",
      "sport": "Snooker",
      "sport_slug": "snooker",
      "sender": "Eurosport",
      "sender_slug": "eurosport",
      "time": "23:00",
      "iso_time": "2026-04-29T23:00:00+02:00",
      "link": "https://play.hbomax.com/sport/9ecc318e-424f-5286-934e-39d5a4ad7747?utm_source=wbd_eurosport_web&utm_campaign=sportsEditorial-program-redirection&utm_medium=owned&utm_content=programsByDate_Program_url",
      "slug": "wm-viertelfinale",
      "related_events": [
        {
          "title": "WM | Wu Yize - Hossein Vafaei",
          "time": "20:00",
          "sender": "Eurosport",
          "slug": "wm-wu-yize-hossein-vafaei"
        }
      ]
    },
    {
      "title": "Tour de Romandie | 1. Etappe",
      "subtitle": "UCI World Tour | Männer | Martigny - Martigny (171,2km)",
      "sport": "Radsport",
      "sport_slug": "radsport",
      "sender": "Eurosport",
      "sender_slug": "eurosport",
      "time": "00:00",
      "iso_time": "2026-04-30T00:00:00+02:00",
      "link": "https://play.hbomax.com/sport/56a1de30-d6a1-51ea-ac88-b65804bd8113?utm_source=wbd_eurosport_web&utm_campaign=sportsEditorial-program-redirection&utm_medium=owned&utm_content=programsByDate_Program_url",
      "slug": "tour-de-romandie-1-etappe",
      "related_events": []
    },
    {
      "title": "Grand Prix Budapest | Highlights",
      "subtitle": "Grand Prix | Männer / Frauen | Degen",
      "sport": "Fechten",
      "sport_slug": "fechten",
      "sender": "Eurosport",
      "sender_slug": "eurosport",
      "time": "00:00",
      "iso_time": "2026-04-30T00:00:00+02:00",
      "link": "https://play.hbomax.com/sport/5f7c6c9a-8fe2-5718-9bc2-d39df7d4927d?utm_source=wbd_eurosport_web&utm_campaign=sportsEditorial-program-redirection&utm_medium=owned&utm_content=programsByDate_Program_url",
      "slug": "grand-prix-budapest-highlights",
      "related_events": []
    },
    {
      "title": "Paris Marathon",
      "subtitle": "49. Austragung | Englischer Kommentar",
      "sport": "Leichtathletik",
      "sport_slug": "leichtathletik",
      "sender": "Eurosport",
      "sender_slug": "eurosport",
      "time": "01:00",
      "iso_time": "2026-04-30T01:00:00+02:00",
      "link": "https://play.hbomax.com/sport/c36fb9eb-c395-5651-839b-0600ccbd8f45?utm_source=wbd_eurosport_web&utm_campaign=sportsEditorial-program-redirection&utm_medium=owned&utm_content=programsByDate_Program_url",
      "slug": "paris-marathon",
      "related_events": []
    }
  ]
}