{
  "date": "2025-12-15",
  "events": [
    {
      "title": "1. FC Union Berlin vs Eintracht Frankfurt",
      "time": "18:00",
      "iso_time": "",
      "sport": "Fußball",
      "sport_slug": "fussball",
      "sender": "Sportschau Live",
      "sender_slug": "sportschau-live",
      "link": "https://www.sportschau.de/live-und-ergebnisse/fussball/deutschland-bundesliga-frauen/ma11376608/1-fc-union-berlin_eintracht-frankfurt/info",
      "slug": "1-fc-union-berlin-vs-eintracht-frankfurt",
      "subtitle": "",
      "related_events": [
        {
          "title": "Fenerbahçe vs Konyaspor",
          "time": "18:00",
          "sender": "Sportschau Live",
          "slug": "fenerbahce-vs-konyaspor"
        }
      ]
    },
    {
      "title": "Manchester United vs AFC Bournemouth",
      "time": "21:00",
      "iso_time": "",
      "sport": "Fußball",
      "sport_slug": "fussball",
      "sender": "Sportschau Live",
      "sender_slug": "sportschau-live",
      "link": "https://www.sportschau.de/live-und-ergebnisse/fussball/england-premier-league/ma11151996/manchester-united_afc-bournemouth/info",
      "slug": "manchester-united-vs-afc-bournemouth",
      "subtitle": "",
      "related_events": [
        {
          "title": "Rayo Vallecano vs Betis Sevilla",
          "time": "21:00",
          "sender": "Sportschau Live",
          "slug": "rayo-vallecano-vs-betis-sevilla"
        }
      ]
    },
    {
      "title": "ROSTOCK SEAWOLVES vs MHP RIESEN Ludwigsburg",
      "time": "20:00",
      "iso_time": "",
      "sport": "Basketball",
      "sport_slug": "basketball",
      "sender": "Sportschau Live",
      "sender_slug": "sportschau-live",
      "link": "https://www.sportschau.de/live-und-ergebnisse/basketball/deutschland-bbl/ma11487521/rostock-seawolves_mhp-riesen-ludwigsburg/info",
      "slug": "rostock-seawolves-vs-mhp-riesen-ludwigsburg",
      "subtitle": "",
      "related_events": []
    },
    {
      "title": "Rayo Vallecano vs Betis Sevilla",
      "time": "21:00",
      "iso_time": "",
      "sport": "Fußball",
      "sport_slug": "fussball",
      "sender": "Sportschau Live",
      "sender_slug": "sportschau-live",
      "link": "https://www.sportschau.de/live-und-ergebnisse/fussball/spanien-primera-division/ma11223332/rayo-vallecano_betis-sevilla/info",
      "slug": "rayo-vallecano-vs-betis-sevilla",
      "subtitle": "",
      "related_events": [
        {
          "title": "Manchester United vs AFC Bournemouth",
          "time": "21:00",
          "sender": "Sportschau Live",
          "slug": "manchester-united-vs-afc-bournemouth"
        }
      ]
    },
    {
      "title": "AS Rom vs Como 1907",
      "time": "20:45",
      "iso_time": "",
      "sport": "Fußball",
      "sport_slug": "fussball",
      "sender": "Sportschau Live",
      "sender_slug": "sportschau-live",
      "link": "https://www.sportschau.de/live-und-ergebnisse/fussball/italien-serie-a/ma11129016/as-rom_como-1907/info",
      "slug": "as-rom-vs-como-1907",
      "subtitle": "",
      "related_events": [
        {
          "title": "Rangers FC vs Hibernian FC",
          "time": "20:45",
          "sender": "Sportschau Live",
          "slug": "rangers-fc-vs-hibernian-fc"
        }
      ]
    },
    {
      "title": "Fenerbahçe vs Konyaspor",
      "time": "18:00",
      "iso_time": "",
      "sport": "Fußball",
      "sport_slug": "fussball",
      "sender": "Sportschau Live",
      "sender_slug": "sportschau-live",
      "link": "https://www.sportschau.de/live-und-ergebnisse/fussball/tuerkei-sueper-lig/ma11303186/fenerbahce_konyaspor/info",
      "slug": "fenerbahce-vs-konyaspor",
      "subtitle": "",
      "related_events": [
        {
          "title": "1. FC Union Berlin vs Eintracht Frankfurt",
          "time": "18:00",
          "sender": "Sportschau Live",
          "slug": "1-fc-union-berlin-vs-eintracht-frankfurt"
        }
      ]
    },
    {
      "title": "Rangers FC vs Hibernian FC",
      "time": "20:45",
      "iso_time": "",
      "sport": "Fußball",
      "sport_slug": "fussball",
      "sender": "Sportschau Live",
      "sender_slug": "sportschau-live",
      "link": "https://www.sportschau.de/live-und-ergebnisse/fussball/schottland-premiership/ma11165445/rangers-fc_hibernian-fc/info",
      "slug": "rangers-fc-vs-hibernian-fc",
      "subtitle": "",
      "related_events": [
        {
          "title": "AS Rom vs Como 1907",
          "time": "20:45",
          "sender": "Sportschau Live",
          "slug": "as-rom-vs-como-1907"
        }
      ]
    },
    {
      "title": "Sporting Braga vs CD Santa Clara",
      "time": "19:45",
      "iso_time": "",
      "sport": "Fußball",
      "sport_slug": "fussball",
      "sender": "Sportschau Live",
      "sender_slug": "sportschau-live",
      "link": "https://www.sportschau.de/live-und-ergebnisse/fussball/portugal-primeira-liga/ma11305667/sporting-braga_cd-santa-clara/info",
      "slug": "sporting-braga-vs-cd-santa-clara",
      "subtitle": "",
      "related_events": []
    },
    {
      "title": "FC Porto vs Estrela Amadora",
      "time": "21:45",
      "iso_time": "",
      "sport": "Fußball",
      "sport_slug": "fussball",
      "sender": "Sportschau Live",
      "sender_slug": "sportschau-live",
      "link": "https://www.sportschau.de/live-und-ergebnisse/fussball/portugal-primeira-liga/ma11305676/fc-porto_estrela-amadora/info",
      "slug": "fc-porto-vs-estrela-amadora",
      "subtitle": "",
      "related_events": []
    },
    {
      "title": "Atlanta Hawks vs Philadelphia 76ers",
      "time": "00:00",
      "iso_time": "",
      "sport": "Basketball",
      "sport_slug": "basketball",
      "sender": "Sportschau Live",
      "sender_slug": "sportschau-live",
      "link": "https://www.sportschau.de/live-und-ergebnisse/basketball/usa-nba/ma11745016/atlanta-hawks_philadelphia-76ers/info",
      "slug": "atlanta-hawks-vs-philadelphia-76ers",
      "subtitle": "",
      "related_events": [
        {
          "title": "Brooklyn Nets vs Milwaukee Bucks",
          "time": "00:00",
          "sender": "Sportschau Live",
          "slug": "brooklyn-nets-vs-milwaukee-bucks"
        }
      ]
    },
    {
      "title": "Brooklyn Nets vs Milwaukee Bucks",
      "time": "00:00",
      "iso_time": "",
      "sport": "Basketball",
      "sport_slug": "basketball",
      "sender": "Sportschau Live",
      "sender_slug": "sportschau-live",
      "link": "https://www.sportschau.de/live-und-ergebnisse/basketball/usa-nba/ma11745022/brooklyn-nets_milwaukee-bucks/info",
      "slug": "brooklyn-nets-vs-milwaukee-bucks",
      "subtitle": "",
      "related_events": [
        {
          "title": "Atlanta Hawks vs Philadelphia 76ers",
          "time": "00:00",
          "sender": "Sportschau Live",
          "slug": "atlanta-hawks-vs-philadelphia-76ers"
        }
      ]
    },
    {
      "title": "Minnesota Timberwolves vs Sacramento Kings",
      "time": "01:00",
      "iso_time": "",
      "sport": "Basketball",
      "sport_slug": "basketball",
      "sender": "Sportschau Live",
      "sender_slug": "sportschau-live",
      "link": "https://www.sportschau.de/live-und-ergebnisse/basketball/usa-nba/ma11745025/minnesota-timberwolves_sacramento-kings/info",
      "slug": "minnesota-timberwolves-vs-sacramento-kings",
      "subtitle": "",
      "related_events": [
        {
          "title": "Chicago Bulls vs New Orleans Pelicans",
          "time": "01:00",
          "sender": "Sportschau Live",
          "slug": "chicago-bulls-vs-new-orleans-pelicans"
        }
      ]
    },
    {
      "title": "Chicago Bulls vs New Orleans Pelicans",
      "time": "01:00",
      "iso_time": "",
      "sport": "Basketball",
      "sport_slug": "basketball",
      "sender": "Sportschau Live",
      "sender_slug": "sportschau-live",
      "link": "https://www.sportschau.de/live-und-ergebnisse/basketball/usa-nba/ma11745028/chicago-bulls_new-orleans-pelicans/info",
      "slug": "chicago-bulls-vs-new-orleans-pelicans",
      "subtitle": "",
      "related_events": [
        {
          "title": "Minnesota Timberwolves vs Sacramento Kings",
          "time": "01:00",
          "sender": "Sportschau Live",
          "slug": "minnesota-timberwolves-vs-sacramento-kings"
        }
      ]
    },
    {
      "title": "Phoenix Suns vs Los Angeles Lakers",
      "time": "02:00",
      "iso_time": "",
      "sport": "Basketball",
      "sport_slug": "basketball",
      "sender": "Sportschau Live",
      "sender_slug": "sportschau-live",
      "link": "https://www.sportschau.de/live-und-ergebnisse/basketball/usa-nba/ma11765440/phoenix-suns_los-angeles-lakers/info",
      "slug": "phoenix-suns-vs-los-angeles-lakers",
      "subtitle": "",
      "related_events": []
    },
    {
      "title": "Portland Trail Blazers vs Golden State Warriors",
      "time": "03:00",
      "iso_time": "",
      "sport": "Basketball",
      "sport_slug": "basketball",
      "sender": "Sportschau Live",
      "sender_slug": "sportschau-live",
      "link": "https://www.sportschau.de/live-und-ergebnisse/basketball/usa-nba/ma11745031/portland-trail-blazers_golden-state-warriors/info",
      "slug": "portland-trail-blazers-vs-golden-state-warriors",
      "subtitle": "",
      "related_events": []
    },
    {
      "title": "Dallas Cowboys vs Minnesota Vikings",
      "time": "02:20",
      "iso_time": "",
      "sport": "American Football",
      "sport_slug": "american-football",
      "sender": "Sportschau Live",
      "sender_slug": "sportschau-live",
      "link": "https://www.sportschau.de/live-und-ergebnisse/football/usa-nfl/ma11091785/dallas-cowboys_minnesota-vikings/info",
      "slug": "dallas-cowboys-vs-minnesota-vikings",
      "subtitle": "",
      "related_events": []
    },
    {
      "title": "Minnesota Wild vs Boston Bruins",
      "time": "00:00",
      "iso_time": "",
      "sport": "Eishockey",
      "sport_slug": "eishockey",
      "sender": "Sportschau Live",
      "sender_slug": "sportschau-live",
      "link": "https://www.sportschau.de/live-und-ergebnisse/eishockey/nhl/ma11413820/minnesota-wild_boston-bruins/info",
      "slug": "minnesota-wild-vs-boston-bruins",
      "subtitle": "",
      "related_events": []
    },
    {
      "title": "Montréal Canadiens vs Edmonton Oilers",
      "time": "01:00",
      "iso_time": "",
      "sport": "Eishockey",
      "sport_slug": "eishockey",
      "sender": "Sportschau Live",
      "sender_slug": "sportschau-live",
      "link": "https://www.sportschau.de/live-und-ergebnisse/eishockey/nhl/ma11413823/montreal-canadiens_edmonton-oilers/info",
      "slug": "montreal-canadiens-vs-edmonton-oilers",
      "subtitle": "",
      "related_events": []
    },
    {
      "title": "Seattle Kraken vs Buffalo Sabres",
      "time": "02:00",
      "iso_time": "",
      "sport": "Eishockey",
      "sport_slug": "eishockey",
      "sender": "Sportschau Live",
      "sender_slug": "sportschau-live",
      "link": "https://www.sportschau.de/live-und-ergebnisse/eishockey/nhl/ma11413826/seattle-kraken_buffalo-sabres/info",
      "slug": "seattle-kraken-vs-buffalo-sabres",
      "subtitle": "",
      "related_events": []
    },
    {
      "title": "Radsport",
      "subtitle": "",
      "sport": "Radsport",
      "sport_slug": "radsport",
      "sender": "Eurosport",
      "sender_slug": "eurosport",
      "time": "23:55",
      "iso_time": "2025-12-14T23:55:44+01:00",
      "link": "https://play.discoveryplus.com/video/watch/8f670e54-e199-51ba-ac02-988ef9820f4b?utm_source=universal_search",
      "slug": "radsport",
      "related_events": []
    },
    {
      "title": "Davos | 10km Freistil",
      "subtitle": "Weltcup | Frauen",
      "sport": "Skilanglauf",
      "sport_slug": "skilanglauf",
      "sender": "Eurosport",
      "sender_slug": "eurosport",
      "time": "00:58",
      "iso_time": "2025-12-15T00:58:03+01:00",
      "link": "",
      "slug": "davos-10km-freistil",
      "related_events": []
    },
    {
      "title": "Val Thorens | Skicross",
      "subtitle": "Weltcup | Frauen / Männer",
      "sport": "Ski Freestyle",
      "sport_slug": "ski-freestyle",
      "sender": "Eurosport",
      "sender_slug": "eurosport",
      "time": "01:27",
      "iso_time": "2025-12-15T01:27:26+01:00",
      "link": "",
      "slug": "val-thorens-skicross",
      "related_events": []
    },
    {
      "title": "Klingenthal | Einzel",
      "subtitle": "Weltcup | Männer | HS 140",
      "sport": "Skispringen",
      "sport_slug": "skispringen",
      "sender": "Eurosport",
      "sender_slug": "eurosport",
      "time": "02:57",
      "iso_time": "2025-12-15T02:57:08+01:00",
      "link": "https://play.discoveryplus.com/video/watch/8d857ba9-9777-5fba-862d-92cd4c339efe?utm_source=universal_search",
      "slug": "klingenthal-einzel",
      "related_events": []
    },
    {
      "title": "T100 Triathlon World Tour | Doha T100",
      "subtitle": "Männer | 9. Station",
      "sport": "Triathlon",
      "sport_slug": "triathlon",
      "sender": "Eurosport",
      "sender_slug": "eurosport",
      "time": "04:29",
      "iso_time": "2025-12-15T04:29:30+01:00",
      "link": "https://play.discoveryplus.com/video/watch/8f139186-ad60-5e07-b1df-df3439cdf707?utm_source=universal_search",
      "slug": "t100-triathlon-world-tour-doha-t100",
      "related_events": []
    },
    {
      "title": "Shoot Out | Finale",
      "subtitle": "Blackpool | European Series",
      "sport": "Snooker",
      "sport_slug": "snooker",
      "sender": "Eurosport",
      "sender_slug": "eurosport",
      "time": "06:35",
      "iso_time": "2025-12-15T06:35:30+01:00",
      "link": "https://play.discoveryplus.com/video/watch/2a9d4269-2ec2-5c02-a74a-7398976d92a8?utm_source=universal_search",
      "slug": "shoot-out-finale",
      "related_events": []
    },
    {
      "title": "Klingenthal | Einzel",
      "subtitle": "Weltcup | Männer | HS 140",
      "sport": "Skispringen",
      "sport_slug": "skispringen",
      "sender": "Eurosport",
      "sender_slug": "eurosport",
      "time": "08:30",
      "iso_time": "2025-12-15T08:30:37+01:00",
      "link": "https://play.discoveryplus.com/video/watch/134a66dd-e199-5cca-bebb-52ae0cc90bb4?utm_source=universal_search",
      "slug": "klingenthal-einzel",
      "related_events": []
    },
    {
      "title": "WM",
      "subtitle": "Finale | Frauen | Rotterdam",
      "sport": "Handball",
      "sport_slug": "handball",
      "sender": "Eurosport",
      "sender_slug": "eurosport",
      "time": "08:32",
      "iso_time": "2025-12-15T08:32:09+01:00",
      "link": "https://play.discoveryplus.com/video/watch/262bcd05-8279-5586-8618-ae6fcf2da41a?utm_source=universal_search",
      "slug": "wm",
      "related_events": []
    },
    {
      "title": "Shoot Out | Finale",
      "subtitle": "Blackpool | European Series",
      "sport": "Snooker",
      "sport_slug": "snooker",
      "sender": "Eurosport",
      "sender_slug": "eurosport",
      "time": "09:25",
      "iso_time": "2025-12-15T09:25:22+01:00",
      "link": "https://play.discoveryplus.com/video/watch/c3dc6226-3d54-5977-9d00-efa81b90a357?utm_source=universal_search",
      "slug": "shoot-out-finale",
      "related_events": [
        {
          "title": "Scottish Open | 1. Runde",
          "time": "11:00",
          "sender": "Eurosport",
          "slug": "scottish-open-1-runde"
        },
        {
          "title": "Scottish Open | 1. Runde",
          "time": "11:00",
          "sender": "Eurosport",
          "slug": "scottish-open-1-runde"
        }
      ]
    },
    {
      "title": "Davos | 10km Freistil",
      "subtitle": "Weltcup | Männer",
      "sport": "Skilanglauf",
      "sport_slug": "skilanglauf",
      "sender": "Eurosport",
      "sender_slug": "eurosport",
      "time": "10:00",
      "iso_time": "2025-12-15T10:00:05+01:00",
      "link": "https://play.discoveryplus.com/video/watch/e38d2609-eaec-57b9-8a9b-f04e08f609e8?utm_source=universal_search",
      "slug": "davos-10km-freistil",
      "related_events": []
    },
    {
      "title": "Klingenthal | Einzel",
      "subtitle": "Weltcup | Männer | HS 140",
      "sport": "Skispringen",
      "sport_slug": "skispringen",
      "sender": "Eurosport",
      "sender_slug": "eurosport",
      "time": "10:31",
      "iso_time": "2025-12-15T10:31:04+01:00",
      "link": "https://play.discoveryplus.com/video/watch/c9ddfaeb-6e2a-5d8f-85e1-8a1827403a48?utm_source=universal_search",
      "slug": "klingenthal-einzel",
      "related_events": []
    },
    {
      "title": "Val Thorens | Skicross",
      "subtitle": "Weltcup | Frauen / Männer",
      "sport": "Ski Freestyle",
      "sport_slug": "ski-freestyle",
      "sender": "Eurosport",
      "sender_slug": "eurosport",
      "time": "10:59",
      "iso_time": "2025-12-15T10:59:08+01:00",
      "link": "https://play.discoveryplus.com/video/watch/dd3f829d-5c1c-5d3c-b364-ba0c2cc03ee7?utm_source=universal_search",
      "slug": "val-thorens-skicross",
      "related_events": []
    },
    {
      "title": "Scottish Open | 1. Runde",
      "subtitle": "Scottish Open | 1. Runde | Edinburgh | Englischer Kommentar",
      "sport": "Snooker",
      "sport_slug": "snooker",
      "sender": "Eurosport",
      "sender_slug": "eurosport",
      "time": "11:00",
      "iso_time": "2025-12-15T11:00:00+01:00",
      "link": "https://play.discoveryplus.com/video/watch/c34d73d9-6325-5e08-a002-e6eaa071773e?utm_source=universal_search",
      "slug": "scottish-open-1-runde",
      "related_events": [
        {
          "title": "Shoot Out | Finale",
          "time": "09:25",
          "sender": "Eurosport",
          "slug": "shoot-out-finale"
        },
        {
          "title": "Shoot Out | Finale",
          "time": "11:55",
          "sender": "Eurosport",
          "slug": "shoot-out-finale"
        },
        {
          "title": "Snooker",
          "time": "14:00",
          "sender": "Eurosport",
          "slug": "snooker"
        }
      ]
    },
    {
      "title": "Scottish Open | 1. Runde",
      "subtitle": "Scottish Open | 1. Runde | Edinburgh | Original Sound",
      "sport": "Snooker",
      "sport_slug": "snooker",
      "sender": "Eurosport",
      "sender_slug": "eurosport",
      "time": "11:00",
      "iso_time": "2025-12-15T11:00:00+01:00",
      "link": "https://play.discoveryplus.com/video/watch/2573f69a-0383-559b-8810-64e7428cac58?utm_source=universal_search",
      "slug": "scottish-open-1-runde",
      "related_events": [
        {
          "title": "Shoot Out | Finale",
          "time": "09:25",
          "sender": "Eurosport",
          "slug": "shoot-out-finale"
        },
        {
          "title": "Shoot Out | Finale",
          "time": "11:55",
          "sender": "Eurosport",
          "slug": "shoot-out-finale"
        },
        {
          "title": "Snooker",
          "time": "14:00",
          "sender": "Eurosport",
          "slug": "snooker"
        }
      ]
    },
    {
      "title": "Shoot Out | Finale",
      "subtitle": "Blackpool | European Series",
      "sport": "Snooker",
      "sport_slug": "snooker",
      "sender": "Eurosport",
      "sender_slug": "eurosport",
      "time": "11:55",
      "iso_time": "2025-12-15T11:55:31+01:00",
      "link": "https://play.discoveryplus.com/video/watch/9cfaf260-b632-5978-9935-6321f7877386?utm_source=universal_search",
      "slug": "shoot-out-finale",
      "related_events": [
        {
          "title": "Scottish Open | 1. Runde",
          "time": "11:00",
          "sender": "Eurosport",
          "slug": "scottish-open-1-runde"
        },
        {
          "title": "Scottish Open | 1. Runde",
          "time": "11:00",
          "sender": "Eurosport",
          "slug": "scottish-open-1-runde"
        },
        {
          "title": "Snooker",
          "time": "14:00",
          "sender": "Eurosport",
          "slug": "snooker"
        }
      ]
    },
    {
      "title": "St. Moritz | Super-G",
      "subtitle": "Weltcup | Frauen",
      "sport": "Ski Alpin",
      "sport_slug": "ski-alpin",
      "sender": "Eurosport",
      "sender_slug": "eurosport",
      "time": "12:00",
      "iso_time": "2025-12-15T12:00:54+01:00",
      "link": "https://play.discoveryplus.com/video/watch/906b9cad-781a-5490-866f-e4cbca86c6cc?utm_source=universal_search",
      "slug": "st-moritz-super-g",
      "related_events": [
        {
          "title": "Val d'Isère | Slalom | 2. Lauf",
          "time": "12:44",
          "sender": "Eurosport",
          "slug": "val-d-isere-slalom-2-lauf"
        }
      ]
    },
    {
      "title": "Val d'Isère | Slalom | 2. Lauf",
      "subtitle": "Weltcup | Männer",
      "sport": "Ski Alpin",
      "sport_slug": "ski-alpin",
      "sender": "Eurosport",
      "sender_slug": "eurosport",
      "time": "12:44",
      "iso_time": "2025-12-15T12:44:46+01:00",
      "link": "https://play.discoveryplus.com/video/watch/11ac42a4-bfd1-5974-ad1a-094257d011b4?utm_source=universal_search",
      "slug": "val-d-isere-slalom-2-lauf",
      "related_events": [
        {
          "title": "St. Moritz | Super-G",
          "time": "12:00",
          "sender": "Eurosport",
          "slug": "st-moritz-super-g"
        }
      ]
    },
    {
      "title": "FIA Awards 2025",
      "subtitle": "Tashkent | Highlights",
      "sport": "Motorsports",
      "sport_slug": "motorsports",
      "sender": "Eurosport",
      "sender_slug": "eurosport",
      "time": "13:31",
      "iso_time": "2025-12-15T13:31:54+01:00",
      "link": "https://play.discoveryplus.com/video/watch/ee19285b-6164-5ebd-98e9-77aaaf8a3780?utm_source=universal_search",
      "slug": "fia-awards-2025",
      "related_events": []
    },
    {
      "title": "Snooker",
      "subtitle": "Scottish Open | 1. Runde",
      "sport": "Snooker",
      "sport_slug": "snooker",
      "sender": "Eurosport",
      "sender_slug": "eurosport",
      "time": "14:00",
      "iso_time": "2025-12-15T14:00:00+01:00",
      "link": "https://play.discoveryplus.com/video/watch/ee0cbd83-580e-5283-a0db-c25499c3e7be?utm_source=universal_search",
      "slug": "snooker",
      "related_events": [
        {
          "title": "Scottish Open | 1. Runde",
          "time": "11:00",
          "sender": "Eurosport",
          "slug": "scottish-open-1-runde"
        },
        {
          "title": "Scottish Open | 1. Runde",
          "time": "11:00",
          "sender": "Eurosport",
          "slug": "scottish-open-1-runde"
        },
        {
          "title": "Shoot Out | Finale",
          "time": "11:55",
          "sender": "Eurosport",
          "slug": "shoot-out-finale"
        }
      ]
    },
    {
      "title": "Scottish Open | 1. Runde",
      "subtitle": "Scottish Open | 1. Runde | Edinburgh | Original Sound",
      "sport": "Snooker",
      "sport_slug": "snooker",
      "sender": "Eurosport",
      "sender_slug": "eurosport",
      "time": "14:00",
      "iso_time": "2025-12-15T14:00:00+01:00",
      "link": "https://play.discoveryplus.com/video/watch/cbbb817e-fdf7-5ede-9017-3ca760815ff6?utm_source=universal_search",
      "slug": "scottish-open-1-runde",
      "related_events": [
        {
          "title": "Shoot Out | Finale",
          "time": "11:55",
          "sender": "Eurosport",
          "slug": "shoot-out-finale"
        },
        {
          "title": "Snooker",
          "time": "14:00",
          "sender": "Eurosport",
          "slug": "snooker"
        }
      ]
    },
    {
      "title": "Scottish Open | 1. Runde",
      "subtitle": "Scottish Open | 1. Runde | Edinburgh | Original Sound",
      "sport": "Snooker",
      "sport_slug": "snooker",
      "sender": "Eurosport",
      "sender_slug": "eurosport",
      "time": "14:00",
      "iso_time": "2025-12-15T14:00:00+01:00",
      "link": "https://play.discoveryplus.com/video/watch/c3dcc493-044e-5401-bbac-b26fd556e56f?utm_source=universal_search",
      "slug": "scottish-open-1-runde",
      "related_events": [
        {
          "title": "Shoot Out | Finale",
          "time": "11:55",
          "sender": "Eurosport",
          "slug": "shoot-out-finale"
        },
        {
          "title": "Snooker",
          "time": "14:00",
          "sender": "Eurosport",
          "slug": "snooker"
        }
      ]
    },
    {
      "title": "Scottish Open | 1. Runde",
      "subtitle": "Scottish Open | 1. Runde | Edinburgh | Original Sound",
      "sport": "Snooker",
      "sport_slug": "snooker",
      "sender": "Eurosport",
      "sender_slug": "eurosport",
      "time": "14:00",
      "iso_time": "2025-12-15T14:00:00+01:00",
      "link": "https://play.discoveryplus.com/video/watch/89f9d1de-856b-519e-a81c-4f70fc867976?utm_source=universal_search",
      "slug": "scottish-open-1-runde",
      "related_events": [
        {
          "title": "Shoot Out | Finale",
          "time": "11:55",
          "sender": "Eurosport",
          "slug": "shoot-out-finale"
        },
        {
          "title": "Snooker",
          "time": "14:00",
          "sender": "Eurosport",
          "slug": "snooker"
        }
      ]
    },
    {
      "title": "Scottish Open | 1. Runde",
      "subtitle": "Scottish Open | 1. Runde | Edinburgh | Home Nations Series",
      "sport": "Snooker",
      "sport_slug": "snooker",
      "sender": "Eurosport",
      "sender_slug": "eurosport",
      "time": "14:00",
      "iso_time": "2025-12-15T14:00:00+01:00",
      "link": "https://play.discoveryplus.com/video/watch/65a75afd-8657-5711-be68-aa3ed1730c9b?utm_source=universal_search",
      "slug": "scottish-open-1-runde",
      "related_events": [
        {
          "title": "Shoot Out | Finale",
          "time": "11:55",
          "sender": "Eurosport",
          "slug": "shoot-out-finale"
        },
        {
          "title": "Snooker",
          "time": "14:00",
          "sender": "Eurosport",
          "slug": "snooker"
        }
      ]
    },
    {
      "title": "Klingenthal",
      "subtitle": "Weltcup | Männer | HS 140",
      "sport": "Skispringen",
      "sport_slug": "skispringen",
      "sender": "Eurosport",
      "sender_slug": "eurosport",
      "time": "14:00",
      "iso_time": "2025-12-15T14:00:00+01:00",
      "link": "https://play.discoveryplus.com/video/watch/5c9f9346-fe7a-5f84-9e95-857d45804bf6?utm_source=universal_search",
      "slug": "klingenthal",
      "related_events": []
    },
    {
      "title": "Davos | 10km Freistil",
      "subtitle": "Weltcup",
      "sport": "Skilanglauf",
      "sport_slug": "skilanglauf",
      "sender": "Eurosport",
      "sender_slug": "eurosport",
      "time": "15:30",
      "iso_time": "2025-12-15T15:30:00+01:00",
      "link": "https://play.discoveryplus.com/video/watch/03d5593a-0ec3-5b36-9dca-de8a52957557?utm_source=universal_search",
      "slug": "davos-10km-freistil",
      "related_events": []
    },
    {
      "title": "Scottish Open | 1. Runde",
      "subtitle": "Scottish Open | 1. Runde | Edinburgh | Original Sound",
      "sport": "Snooker",
      "sport_slug": "snooker",
      "sender": "Eurosport",
      "sender_slug": "eurosport",
      "time": "16:00",
      "iso_time": "2025-12-15T16:00:00+01:00",
      "link": "https://play.discoveryplus.com/video/watch/f4f90446-06bb-5d9b-a28a-bcb049276f9c?utm_source=universal_search",
      "slug": "scottish-open-1-runde",
      "related_events": [
        {
          "title": "Snooker",
          "time": "14:00",
          "sender": "Eurosport",
          "slug": "snooker"
        }
      ]
    },
    {
      "title": "Scottish Open | 1. Runde",
      "subtitle": "Scottish Open | 1. Runde | Edinburgh | Home Nations Series",
      "sport": "Snooker",
      "sport_slug": "snooker",
      "sender": "Eurosport",
      "sender_slug": "eurosport",
      "time": "16:00",
      "iso_time": "2025-12-15T16:00:00+01:00",
      "link": "https://play.discoveryplus.com/video/watch/4a19ad8d-bdbe-5f86-b26b-a41ba9fc1eb9?utm_source=universal_search",
      "slug": "scottish-open-1-runde",
      "related_events": [
        {
          "title": "Snooker",
          "time": "14:00",
          "sender": "Eurosport",
          "slug": "snooker"
        }
      ]
    },
    {
      "title": "Scottish Open | 1. Runde",
      "subtitle": "Scottish Open | 1. Runde | Edinburgh | Original Sound",
      "sport": "Snooker",
      "sport_slug": "snooker",
      "sender": "Eurosport",
      "sender_slug": "eurosport",
      "time": "16:00",
      "iso_time": "2025-12-15T16:00:00+01:00",
      "link": "https://play.discoveryplus.com/video/watch/01b3b5a6-7929-5b04-8aa3-acc20d849ee9?utm_source=universal_search",
      "slug": "scottish-open-1-runde",
      "related_events": [
        {
          "title": "Snooker",
          "time": "14:00",
          "sender": "Eurosport",
          "slug": "snooker"
        }
      ]
    },
    {
      "title": "Davos | 10km Freistil",
      "subtitle": "Weltcup",
      "sport": "Skilanglauf",
      "sport_slug": "skilanglauf",
      "sender": "Eurosport",
      "sender_slug": "eurosport",
      "time": "16:30",
      "iso_time": "2025-12-15T16:30:00+01:00",
      "link": "https://play.discoveryplus.com/video/watch/fa7155ad-6091-5252-952d-daf7601768eb?utm_source=universal_search",
      "slug": "davos-10km-freistil",
      "related_events": []
    },
    {
      "title": "Val Thorens | Skicross",
      "subtitle": "Weltcup | Frauen Männer",
      "sport": "Ski Freestyle",
      "sport_slug": "ski-freestyle",
      "sender": "Eurosport",
      "sender_slug": "eurosport",
      "time": "17:00",
      "iso_time": "2025-12-15T17:00:00+01:00",
      "link": "https://play.discoveryplus.com/video/watch/e3384399-cadf-5fcc-9a60-86a43ff0ca94?utm_source=universal_search",
      "slug": "val-thorens-skicross",
      "related_events": []
    },
    {
      "title": "Triathlon: T100 Triathlon World Tour in Doha",
      "subtitle": "",
      "sport": "Triathlon",
      "sport_slug": "triathlon",
      "sender": "Eurosport",
      "sender_slug": "eurosport",
      "time": "18:00",
      "iso_time": "2025-12-15T18:00:00+01:00",
      "link": "https://play.discoveryplus.com/video/watch/8b8cb27e-31aa-5e10-967f-837d00ca01e5?utm_source=universal_search",
      "slug": "triathlon-t100-triathlon-world-tour-in-doha",
      "related_events": []
    },
    {
      "title": "St. Moritz | Super-G",
      "subtitle": "Weltcup | Frauen",
      "sport": "Ski Alpin",
      "sport_slug": "ski-alpin",
      "sender": "Eurosport",
      "sender_slug": "eurosport",
      "time": "18:00",
      "iso_time": "2025-12-15T18:00:00+01:00",
      "link": "https://play.discoveryplus.com/video/watch/2c622b08-a6c3-52cc-aebc-89e67fc3ba8e?utm_source=universal_search",
      "slug": "st-moritz-super-g",
      "related_events": [
        {
          "title": "Val d'Isère | Slalom | 1. Lauf",
          "time": "18:45",
          "sender": "Eurosport",
          "slug": "val-d-isere-slalom-1-lauf"
        },
        {
          "title": "Val d'Isère | Slalom | 2. Lauf",
          "time": "19:15",
          "sender": "Eurosport",
          "slug": "val-d-isere-slalom-2-lauf"
        }
      ]
    },
    {
      "title": "Val d'Isère | Slalom | 1. Lauf",
      "subtitle": "Weltcup | Männer",
      "sport": "Ski Alpin",
      "sport_slug": "ski-alpin",
      "sender": "Eurosport",
      "sender_slug": "eurosport",
      "time": "18:45",
      "iso_time": "2025-12-15T18:45:00+01:00",
      "link": "https://play.discoveryplus.com/video/watch/14bf98c4-8f9d-5421-9196-77734f3398d5?utm_source=universal_search",
      "slug": "val-d-isere-slalom-1-lauf",
      "related_events": [
        {
          "title": "St. Moritz | Super-G",
          "time": "18:00",
          "sender": "Eurosport",
          "slug": "st-moritz-super-g"
        },
        {
          "title": "Val d'Isère | Slalom | 2. Lauf",
          "time": "19:15",
          "sender": "Eurosport",
          "slug": "val-d-isere-slalom-2-lauf"
        }
      ]
    },
    {
      "title": "Val d'Isère | Slalom | 2. Lauf",
      "subtitle": "Weltcup | Männer",
      "sport": "Ski Alpin",
      "sport_slug": "ski-alpin",
      "sender": "Eurosport",
      "sender_slug": "eurosport",
      "time": "19:15",
      "iso_time": "2025-12-15T19:15:00+01:00",
      "link": "https://play.discoveryplus.com/video/watch/e79713a1-dd16-513e-b3d5-5913262b43f4?utm_source=universal_search",
      "slug": "val-d-isere-slalom-2-lauf",
      "related_events": [
        {
          "title": "St. Moritz | Super-G",
          "time": "18:00",
          "sender": "Eurosport",
          "slug": "st-moritz-super-g"
        },
        {
          "title": "Val d'Isère | Slalom | 1. Lauf",
          "time": "18:45",
          "sender": "Eurosport",
          "slug": "val-d-isere-slalom-1-lauf"
        }
      ]
    },
    {
      "title": "Snooker",
      "subtitle": "Scottish Open | 1. Runde",
      "sport": "Snooker",
      "sport_slug": "snooker",
      "sender": "Eurosport",
      "sender_slug": "eurosport",
      "time": "20:00",
      "iso_time": "2025-12-15T20:00:00+01:00",
      "link": "https://play.discoveryplus.com/video/watch/6d2ccc0a-7f41-56a4-abc1-8f93b39600d8?utm_source=universal_search",
      "slug": "snooker",
      "related_events": [
        {
          "title": "Scottish Open | 1. Runde",
          "time": "20:00",
          "sender": "Eurosport",
          "slug": "scottish-open-1-runde"
        },
        {
          "title": "Scottish Open | 1. Runde",
          "time": "20:00",
          "sender": "Eurosport",
          "slug": "scottish-open-1-runde"
        },
        {
          "title": "Scottish Open | 1. Runde",
          "time": "20:00",
          "sender": "Eurosport",
          "slug": "scottish-open-1-runde"
        }
      ]
    },
    {
      "title": "Scottish Open | 1. Runde",
      "subtitle": "Scottish Open | 1. Runde | Edinburgh | Original Sound",
      "sport": "Snooker",
      "sport_slug": "snooker",
      "sender": "Eurosport",
      "sender_slug": "eurosport",
      "time": "20:00",
      "iso_time": "2025-12-15T20:00:00+01:00",
      "link": "https://play.discoveryplus.com/video/watch/a8b77a38-ce16-504d-8384-2c6f5569a6f2?utm_source=universal_search",
      "slug": "scottish-open-1-runde",
      "related_events": [
        {
          "title": "Snooker",
          "time": "20:00",
          "sender": "Eurosport",
          "slug": "snooker"
        }
      ]
    },
    {
      "title": "Scottish Open | 1. Runde",
      "subtitle": "Scottish Open | 1. Runde | Edinburgh | Original Sound",
      "sport": "Snooker",
      "sport_slug": "snooker",
      "sender": "Eurosport",
      "sender_slug": "eurosport",
      "time": "20:00",
      "iso_time": "2025-12-15T20:00:00+01:00",
      "link": "https://play.discoveryplus.com/video/watch/2e92dc60-e1dc-5d7d-852c-2e63a90a5b66?utm_source=universal_search",
      "slug": "scottish-open-1-runde",
      "related_events": [
        {
          "title": "Snooker",
          "time": "20:00",
          "sender": "Eurosport",
          "slug": "snooker"
        }
      ]
    },
    {
      "title": "Scottish Open | 1. Runde",
      "subtitle": "Scottish Open | 1. Runde | Edinburgh | Home Nations Series",
      "sport": "Snooker",
      "sport_slug": "snooker",
      "sender": "Eurosport",
      "sender_slug": "eurosport",
      "time": "20:00",
      "iso_time": "2025-12-15T20:00:00+01:00",
      "link": "https://play.discoveryplus.com/video/watch/17c2da84-8643-5860-9df0-51da89548fc3?utm_source=universal_search",
      "slug": "scottish-open-1-runde",
      "related_events": [
        {
          "title": "Snooker",
          "time": "20:00",
          "sender": "Eurosport",
          "slug": "snooker"
        }
      ]
    },
    {
      "title": "Klingenthal",
      "subtitle": "Weltcup | Männer | HS 140",
      "sport": "Skispringen",
      "sport_slug": "skispringen",
      "sender": "Eurosport",
      "sender_slug": "eurosport",
      "time": "20:00",
      "iso_time": "2025-12-15T20:00:00+01:00",
      "link": "https://play.discoveryplus.com/video/watch/1ed2f8b0-7cbf-597a-9204-7e999c9aa464?utm_source=universal_search",
      "slug": "klingenthal",
      "related_events": []
    },
    {
      "title": "Davos | 10km Freistil",
      "subtitle": "Weltcup",
      "sport": "Skilanglauf",
      "sport_slug": "skilanglauf",
      "sender": "Eurosport",
      "sender_slug": "eurosport",
      "time": "21:30",
      "iso_time": "2025-12-15T21:30:00+01:00",
      "link": "https://play.discoveryplus.com/video/watch/a0c8b1ba-a028-5368-b9db-edaf437db8f7?utm_source=universal_search",
      "slug": "davos-10km-freistil",
      "related_events": []
    },
    {
      "title": "Scottish Open | 1. Runde",
      "subtitle": "Scottish Open | 1. Runde | Edinburgh | Home Nations Series",
      "sport": "Snooker",
      "sport_slug": "snooker",
      "sender": "Eurosport",
      "sender_slug": "eurosport",
      "time": "22:00",
      "iso_time": "2025-12-15T22:00:00+01:00",
      "link": "https://play.discoveryplus.com/video/watch/a603169c-1e19-5389-8213-27167018082f?utm_source=universal_search",
      "slug": "scottish-open-1-runde",
      "related_events": [
        {
          "title": "Snooker",
          "time": "20:00",
          "sender": "Eurosport",
          "slug": "snooker"
        }
      ]
    },
    {
      "title": "Scottish Open | 1. Runde",
      "subtitle": "Scottish Open | 1. Runde | Edinburgh | Original Sound",
      "sport": "Snooker",
      "sport_slug": "snooker",
      "sender": "Eurosport",
      "sender_slug": "eurosport",
      "time": "22:00",
      "iso_time": "2025-12-15T22:00:00+01:00",
      "link": "https://play.discoveryplus.com/video/watch/710b4347-082a-5d49-bd10-2151c4a27e13?utm_source=universal_search",
      "slug": "scottish-open-1-runde",
      "related_events": [
        {
          "title": "Snooker",
          "time": "20:00",
          "sender": "Eurosport",
          "slug": "snooker"
        }
      ]
    },
    {
      "title": "Davos | 10km Freistil",
      "subtitle": "Weltcup",
      "sport": "Skilanglauf",
      "sport_slug": "skilanglauf",
      "sender": "Eurosport",
      "sender_slug": "eurosport",
      "time": "22:30",
      "iso_time": "2025-12-15T22:30:00+01:00",
      "link": "https://play.discoveryplus.com/video/watch/1f9eda68-da47-55ae-8ba3-3de323640eb6?utm_source=universal_search",
      "slug": "davos-10km-freistil",
      "related_events": []
    },
    {
      "title": "Val Thorens | Skicross",
      "subtitle": "Weltcup | Frauen Männer",
      "sport": "Ski Freestyle",
      "sport_slug": "ski-freestyle",
      "sender": "Eurosport",
      "sender_slug": "eurosport",
      "time": "23:00",
      "iso_time": "2025-12-15T23:00:00+01:00",
      "link": "https://play.discoveryplus.com/video/watch/9399edb7-67eb-5a83-8857-7cf86f0a8588?utm_source=universal_search",
      "slug": "val-thorens-skicross",
      "related_events": []
    },
    {
      "title": "Triathlon: T100 Triathlon World Tour in Doha",
      "subtitle": "",
      "sport": "Triathlon",
      "sport_slug": "triathlon",
      "sender": "Eurosport",
      "sender_slug": "eurosport",
      "time": "00:00",
      "iso_time": "2025-12-16T00:00:00+01:00",
      "link": "https://play.discoveryplus.com/video/watch/ccf4df37-b81f-578f-b6e3-0f92f30230e5?utm_source=universal_search",
      "slug": "triathlon-t100-triathlon-world-tour-in-doha",
      "related_events": []
    },
    {
      "title": "Klingenthal",
      "subtitle": "Weltcup | Männer | HS 140",
      "sport": "Skispringen",
      "sport_slug": "skispringen",
      "sender": "Eurosport",
      "sender_slug": "eurosport",
      "time": "00:00",
      "iso_time": "2025-12-16T00:00:00+01:00",
      "link": "https://play.discoveryplus.com/video/watch/f34bb6f2-e500-520f-8ec6-81ae9e14327d?utm_source=universal_search",
      "slug": "klingenthal",
      "related_events": []
    }
  ]
}